Workbook

Sheet Cover
B2: [TOKEN] — Crypto / Digital Asset Model
B4: Protocol: | C4: [fill in]
B5: Chain / L1-L2: | C5: [fill in]
B6: Last refreshed: | C6: [date]
B7: Next unlock/emission event: | C7: [date]
B8: Refresh cadence: | C8: Weekly (daily around unlocks)

Sheet Tokenomics
B2: Tokenomics — Supply Schedule
B4: Allocation | C4: Tokens | D4: % of max supply | E4: Unlock start | F4: Vesting notes
B5: Public / community | C5: 0 | D5: =IFERROR(C5/$C$10,"-") -> - | E5: [date] | F5: [cliff / linear vesting terms]
B6: Team & advisors | C6: 0 | D6: =IFERROR(C6/$C$10,"-") -> - | E6: [date] | F6: [cliff / linear vesting terms]
B7: Investors (seed/private) | C7: 0 | D7: =IFERROR(C7/$C$10,"-") -> - | E7: [date] | F7: [cliff / linear vesting terms]
B8: Treasury / foundation | C8: 0 | D8: =IFERROR(C8/$C$10,"-") -> - | E8: [date] | F8: [cliff / linear vesting terms]
B9: Ecosystem incentives / staking rewards | C9: 0 | D9: =IFERROR(C9/$C$10,"-") -> - | E9: [date] | F9: [cliff / linear vesting terms]
B10: Max supply | C10: =SUM(C5:C9) -> 0
B12: Circulating supply (today) | C12: 0
B13: Circulating / max supply % | C13: =IFERROR(C12/C10,"-") -> -

Sheet Valuation
B2: On-Chain Valuation Multiples
B4: Inputs
B5: Token price | C5: 0
B6: Total value locked (TVL, $) | C6: 0
B7: Annualized protocol revenue/fees ($) | C7: 0
B8: Daily transaction volume ($, trailing 30d avg) | C8: 0
B10: Outputs
B11: Market cap (circulating) | C11: =C5*Tokenomics!C12 -> 0
B12: Fully diluted valuation (FDV) | C12: =C5*Tokenomics!C10 -> 0
B13: Market cap / TVL | C13: =IFERROR(C11/C6,"-") -> -
B14: FDV / TVL | C14: =IFERROR(C12/C6,"-") -> -
B15: P/S equivalent (Mkt cap / annualized revenue) | C15: =IFERROR(C11/C7,"-") -> -
B16: NVT ratio (Mkt cap / daily volume, annualized) | C16: =IFERROR(C11/(C8*365),"-") -> - | D16: High NVT = valuation rich relative to network usage (P/E-style read)

Sheet Staking Yield
B2: Staking / Yield Model
B4: Inputs
B5: % of supply staked | C5: 0
B6: Annual token emissions (new supply, tokens) | C6: 0
B7: Protocol fee revenue distributed to stakers ($) | C7: 0
B8: Token price (for $ yield calc) | C8: 0
B10: Outputs
B11: Tokens staked | C11: =C5*Tokenomics!C12 -> 0
B12: Inflationary yield (emissions / staked) | C12: =IFERROR(C6/C11,"-") -> -
B13: Real yield (fee revenue / staked value) | C13: =IFERROR(C7/(C11*C8),"-") -> -
B14: Net staking yield (real - inflation dilution) | C14: =IFERROR(C13-C12,"-") -> - | D14: Negative = staking rewards are pure dilution, not real cash flow

Sheet Comparable Protocols
B2: Comparable Protocols
B4: Protocol | C4: Mkt cap | D4: FDV | E4: TVL | F4: Daily volume | G4: Mkt/TVL | H4: FDV/TVL | I4: NVT
B5: This protocol | C5: =Valuation!C11 -> 0 | D5: =Valuation!C12 -> 0 | E5: =Valuation!C6 -> 0 | F5: =Valuation!C8 -> 0 | G5: =IFERROR(C5/E5,"-") -> - | H5: =IFERROR(D5/E5,"-") -> - | I5: =IFERROR(C5/(F5*365),"-") -> -
B6: [fill in] | C6: 0 | D6: 0 | E6: 0 | F6: 0 | G6: =IFERROR(C6/E6,"-") -> - | H6: =IFERROR(D6/E6,"-") -> - | I6: =IFERROR(C6/(F6*365),"-") -> -
B7: [fill in] | C7: 0 | D7: 0 | E7: 0 | F7: 0 | G7: =IFERROR(C7/E7,"-") -> - | H7: =IFERROR(D7/E7,"-") -> - | I7: =IFERROR(C7/(F7*365),"-") -> -
B8: [fill in] | C8: 0 | D8: 0 | E8: 0 | F8: 0 | G8: =IFERROR(C8/E8,"-") -> - | H8: =IFERROR(D8/E8,"-") -> - | I8: =IFERROR(C8/(F8*365),"-") -> -
B9: [fill in] | C9: 0 | D9: 0 | E9: 0 | F9: 0 | G9: =IFERROR(C9/E9,"-") -> - | H9: =IFERROR(D9/E9,"-") -> - | I9: =IFERROR(C9/(F9*365),"-") -> -
B10: [fill in] | C10: 0 | D10: 0 | E10: 0 | F10: 0 | G10: =IFERROR(C10/E10,"-") -> - | H10: =IFERROR(D10/E10,"-") -> - | I10: =IFERROR(C10/(F10*365),"-") -> -
B11: [fill in] | C11: 0 | D11: 0 | E11: 0 | F11: 0 | G11: =IFERROR(C11/E11,"-") -> - | H11: =IFERROR(D11/E11,"-") -> - | I11: =IFERROR(C11/(F11*365),"-") -> -

Sheet Supply Emission Schedule
B2: Forward Supply Emission & Dilution
B4: Annual emission rate (% of max supply issued/yr) | C4: 0.05 | D4: Simplified: assumes a flat schedule. Real unlocks are usually cliff + linear per allocation — treat this as a planning approximation, not a substitute for the actual unlock table.
C6: Period 0 | D6: Period 1 | E6: Period 2 | F6: Period 3 | G6: Period 4
B7: Circulating supply | C7: =Tokenomics!C12 -> 0 | D7: =MIN(Tokenomics!$C$10,C7+Tokenomics!$C$10*$C$4) -> 0 | E7: =MIN(Tokenomics!$C$10,D7+Tokenomics!$C$10*$C$4) -> 0 | F7: =MIN(Tokenomics!$C$10,E7+Tokenomics!$C$10*$C$4) -> 0 | G7: =MIN(Tokenomics!$C$10,F7+Tokenomics!$C$10*$C$4) -> 0
B8: Cumulative dilution vs. today | C8: =IFERROR(1-$C$7/C7,"-") -> - | D8: =IFERROR(1-$C$7/D7,"-") -> - | E8: =IFERROR(1-$C$7/E7,"-") -> - | F8: =IFERROR(1-$C$7/F7,"-") -> - | G8: =IFERROR(1-$C$7/G7,"-") -> -
B9: Implied mkt cap at today's price (if price held flat) | C9: =Valuation!$C$5*C7 -> 0 | D9: =Valuation!$C$5*D7 -> 0 | E9: =Valuation!$C$5*E7 -> 0 | F9: =Valuation!$C$5*F7 -> 0 | G9: =Valuation!$C$5*G7 -> 0
B10: A holder who doesn't add to their position loses this much ownership share to new issuance over time -- the price needs to grow faster than dilution just to keep the position's dollar value from falling.

Sheet RefreshLog
B2: Refresh Log
B4: Date | C4: Trigger | D4: What changed | E4: Reviewer notes | F4: Next check
