Workbook

Sheet Cover
B2: [PROPERTY/REIT] — Real Estate Model
B4: Property type: | C4: Office / Multifamily / Industrial / Retail
B5: Location: | C5: [fill in]
B6: Last refreshed: | C6: [date]
B7: Refresh cadence: | C7: Weekly

Sheet Property Pro Forma
B2: Property Pro Forma (annual, $)
B5: Gross potential rent | C5: 0
B6: - Vacancy & credit loss | C6: 0
B7: Effective gross income | C7: =C5+C6 -> 0
B8: + Other income (parking, fees) | C8: 0
B9: Total revenue | C9: =C7+C8 -> 0
B10: - Operating expenses (taxes, insurance, mgmt, R&M) | C10: 0
B11: Net Operating Income (NOI) | C11: =C9+C10 -> 0
B12: - Capex reserve | C12: 0
B13: - Debt service (P&I) | C13: 0
B14: Cash flow before tax | C14: =C11+C12+C13 -> 0

Sheet Cap Rate & Valuation
B2: Cap Rate Valuation
B4: NOI (from pro forma) | C4: ='Property Pro Forma'!C11 -> 0
B5: Market cap rate % | C5: 0.06
B6: Implied value (NOI / cap rate) | C6: =IFERROR(C4/C5,"-") -> 0
B8: Purchase price ($) | C8: 0
B9: Going-in cap rate (NOI / price) | C9: =IFERROR(C4/C8,"-") -> -
B10: Debt amount | C10: 0
B11: Cash-on-cash return | C11: =IFERROR('Property Pro Forma'!C14/(C8-C10),"-") -> -

Sheet REIT FFO-AFFO
B2: REIT FFO / AFFO
B4: Net income (GAAP) | C4: 0
B5: + Real estate depreciation & amortization | C5: 0
B6: - Gains on property sales | C6: 0
B7: FFO (Funds From Operations) | C7: =C4+C5+C6 -> 0
B9: - Recurring capex / leasing costs | C9: 0
B10: - Straight-line rent adjustment | C10: 0
B11: AFFO (Adjusted FFO) | C11: =C7+C9+C10 -> 0 | D11: AFFO is the better proxy for sustainable dividend-paying capacity
B13: Shares/units outstanding | C13: 1
B14: FFO / share | C14: =IFERROR(C7/C13,"-") -> 0
B15: AFFO / share | C15: =IFERROR(C11/C13,"-") -> 0

Sheet 5-Year Hold & IRR
B2: 5-Year Hold — Levered Cash Flow & IRR
B4: Assumptions
B5: NOI growth rate (%/yr) | C5: 0.02
B6: Exit cap rate (%) | C6: 0.065
B7: Selling costs (% of exit value) | C7: 0.02
B8: Annual debt service ($, assumed constant / interest-only) | C8: =IFERROR(ABS('Property Pro Forma'!C13),"-") -> 0
B9: Initial equity (purchase price - debt) | C9: =IFERROR('Cap Rate & Valuation'!C8-'Cap Rate & Valuation'!C10,"-") -> 0
C12: Yr1 | D12: Yr2 | E12: Yr3 | F12: Yr4 | G12: Yr5
B13: NOI | C13: ='Property Pro Forma'!C11 -> 0 | D13: =C13*(1+$C$5) -> 0 | E13: =D13*(1+$C$5) -> 0 | F13: =E13*(1+$C$5) -> 0 | G13: =F13*(1+$C$5) -> 0
B14: Debt service | C14: =$C$8 -> 0 | D14: =$C$8 -> 0 | E14: =$C$8 -> 0 | F14: =$C$8 -> 0 | G14: =$C$8 -> 0
B15: Levered cash flow | C15: =C13-C14 -> 0 | D15: =D13-D14 -> 0 | E15: =E13-E14 -> 0 | F15: =F13-F14 -> 0 | G15: =G13-G14 -> 0
B16: DSCR (NOI / debt service) | C16: =IFERROR(C13/C14,"-") -> - | D16: =IFERROR(D13/D14,"-") -> - | E16: =IFERROR(E13/E14,"-") -> - | F16: =IFERROR(F13/F14,"-") -> - | G16: =IFERROR(G13/G14,"-") -> -
B18: Exit (end of Yr5)
B19: Forward NOI (Yr6, for exit cap) | C19: =G13*(1+$C$5) -> 0
B20: Exit value (forward NOI / exit cap rate) | C20: =IFERROR(C19/C6,"-") -> 0
B21: Less: selling costs | C21: =-C20*C7 -> 0
B22: Less: debt payoff (assumed interest-only, balance unchanged) | C22: =-'Cap Rate & Valuation'!C10 -> 0
B23: Net exit equity proceeds | C23: =C20+C21+C22 -> 0
C25: Yr0 | D25: Yr1 | E25: Yr2 | F25: Yr3 | G25: Yr4 | H25: Yr5
B26: Equity cash flow | C26: =-C9 -> 0 | D26: =C15 -> 0 | E26: =D15 -> 0 | F26: =E15 -> 0 | G26: =F15 -> 0 | H26: =G15+C23 -> 0
B27: Levered IRR | C27: =IFERROR(IRR(C26:H26),"-") -> -
B28: Equity multiple (MOIC) | C28: =IFERROR(SUM(D26:H26)/C9,"-") -> -

Sheet RefreshLog
B2: Refresh Log
B4: Date | C4: Trigger | D4: What changed | E4: Reviewer notes | F4: Next check
