Workbook

Sheet Cover
B2: ACME — Illustrative Demo Instance
B4: Sector: | C4: Consumer / Industrials (fictional)
B5: Coverage started: | C5: 2026-06-01
B6: Last refreshed: | C6: 2026-08-01
B7: Next earnings date: | C7: 2026-11-05
B8: Refresh cadence: | C8: Weekly
B10: Thesis (2-3 sentences):
B11: DEMO INSTANCE — Acme Corp is a fictional company; all figures below are illustrative, not real market data. Built to demonstrate the full 3-statement + DCF linkage and the weekly refresh workflow end to end, not as investment research.
B16: COLOR LEGEND
B17: Blue text | C17: Hardcoded input / scenario lever — edit freely
B18: Black text | C18: Formula — do not overwrite
B19: Green text | C19: Link to another sheet in this workbook
B20: Yellow fill | C20: Key assumption — review every refresh

Sheet Assumptions
B2: Assumptions
B4: Driver | C4: FY1 | D4: FY2 | E4: FY3 | F4: FY4 | G4: FY5 | H4: Source / notes
B5: Revenue growth % | C5: 0.08 | D5: 0.07 | E5: 0.06 | F5: 0.06 | G5: 0.05 | H5: Source: [10-K/10-Q cite or user estimate]
B6: Gross margin % | C6: 0.58 | D6: 0.58 | E6: 0.58 | F6: 0.58 | G6: 0.58 | H6: Source: [10-K/10-Q cite or user estimate]
B7: Opex % of revenue | C7: 0.24 | D7: 0.24 | E7: 0.24 | F7: 0.24 | G7: 0.24 | H7: Source: [10-K/10-Q cite or user estimate]
B8: Tax rate % | C8: 0.25 | D8: 0.25 | E8: 0.25 | F8: 0.25 | G8: 0.25 | H8: Source: [10-K/10-Q cite or user estimate]
B9: D&A % of capex | C9: 0.75 | D9: 0.75 | E9: 0.75 | F9: 0.75 | G9: 0.75 | H9: Source: [10-K/10-Q cite or user estimate]
B10: Capex % of revenue | C10: 0.045 | D10: 0.045 | E10: 0.045 | F10: 0.045 | G10: 0.045 | H10: Source: [10-K/10-Q cite or user estimate]
B11: NWC % of revenue chg | C11: 0.02 | D11: 0.02 | E11: 0.02 | F11: 0.02 | G11: 0.02 | H11: Source: [10-K/10-Q cite or user estimate]
B12: Shares outstanding (mm) | C12: 100 | D12: 100 | E12: 100 | F12: 100 | G12: 100 | H12: Source: [10-K/10-Q cite or user estimate]
B13: WACC % | C13: 0.095 | D13: 0.095 | E13: 0.095 | F13: 0.095 | G13: 0.095 | H13: Source: [10-K/10-Q cite or user estimate]
B14: Terminal growth % | C14: 0.025 | D14: 0.025 | E14: 0.025 | F14: 0.025 | G14: 0.025 | H14: Source: [10-K/10-Q cite or user estimate]

Sheet IS
B2: Income Statement ($mm)
B4: Line item | C4: FY-2A | D4: FY-1A | E4: FY0A | F4: FY1E | G4: FY2E | H4: FY3E | I4: FY4E
B5: Revenue | C5: 850 | D5: 920 | E5: 1000 | F5: =E5*(1+Assumptions!C5) -> 1080 | G5: =F5*(1+Assumptions!D5) -> 1155.6 | H5: =G5*(1+Assumptions!E5) -> 1224.936 | I5: =H5*(1+Assumptions!F5) -> 1298.4322
B6: Revenue growth % | D6: =IFERROR(D5/C5-1,"-") -> 0.082352941 | E6: =IFERROR(E5/D5-1,"-") -> 0.086956522 | F6: =IFERROR(F5/E5-1,"-") -> 0.08 | G6: =IFERROR(G5/F5-1,"-") -> 0.07 | H6: =IFERROR(H5/G5-1,"-") -> 0.06 | I6: =IFERROR(I5/H5-1,"-") -> 0.06
B7: COGS | E7: 420 | F7: =F5*(1-Assumptions!C6) -> 453.6 | G7: =G5*(1-Assumptions!D6) -> 485.352 | H7: =H5*(1-Assumptions!E6) -> 514.47312 | I7: =I5*(1-Assumptions!F6) -> 545.34151
B8: Gross profit | D8: =D5-D7 -> 920 | E8: =E5-E7 -> 580 | F8: =F5-F7 -> 626.4 | G8: =G5-G7 -> 670.248 | H8: =H5-H7 -> 710.46288 | I8: =I5-I7 -> 753.09065
B9: Gross margin % | D9: =IFERROR(D8/D5,"-") -> 1 | E9: =IFERROR(E8/E5,"-") -> 0.58 | F9: =IFERROR(F8/F5,"-") -> 0.58 | G9: =IFERROR(G8/G5,"-") -> 0.58 | H9: =IFERROR(H8/H5,"-") -> 0.58 | I9: =IFERROR(I8/I5,"-") -> 0.58
B10: Opex | E10: 240 | F10: =F5*Assumptions!C7 -> 259.2 | G10: =G5*Assumptions!D7 -> 277.344 | H10: =H5*Assumptions!E7 -> 293.98464 | I10: =I5*Assumptions!F7 -> 311.62372
B11: EBITDA | E11: =E8-E10 -> 340 | F11: =F8-F10 -> 367.2 | G11: =G8-G10 -> 392.904 | H11: =H8-H10 -> 416.47824 | I11: =I8-I10 -> 441.46693
B12: EBITDA margin % | F12: =IFERROR(F11/F5,"-") -> 0.34 | G12: =IFERROR(G11/G5,"-") -> 0.34 | H12: =IFERROR(H11/H5,"-") -> 0.34 | I12: =IFERROR(I11/I5,"-") -> 0.34
B13: D&A | E13: 45 | F13: =F5*Assumptions!C10*Assumptions!C9 -> 36.45 | G13: =G5*Assumptions!D10*Assumptions!D9 -> 39.0015 | H13: =H5*Assumptions!E10*Assumptions!E9 -> 41.34159 | I13: =I5*Assumptions!F10*Assumptions!F9 -> 43.822085
B14: EBIT | E14: =E11-E13 -> 295 | F14: =F11-F13 -> 330.75 | G14: =G11-G13 -> 353.9025 | H14: =H11-H13 -> 375.13665 | I14: =I11-I13 -> 397.64485
B15: Interest expense | E15: 20 | F15: =$E$15 -> 20 | G15: =$E$15 -> 20 | H15: =$E$15 -> 20 | I15: =$E$15 -> 20
B16: Pre-tax income | E16: =E14-E15 -> 275 | F16: =F14-F15 -> 310.75 | G16: =G14-G15 -> 333.9025 | H16: =H14-H15 -> 355.13665 | I16: =I14-I15 -> 377.64485
B17: Tax | E17: =E16*0.25 -> 68.75 | F17: =F16*Assumptions!C8 -> 77.6875 | G17: =G16*Assumptions!D8 -> 83.475625 | H17: =H16*Assumptions!E8 -> 88.784162 | I17: =I16*Assumptions!F8 -> 94.411212
B18: Net income | E18: =E16-E17 -> 206.25 | F18: =F16-F17 -> 233.0625 | G18: =G16-G17 -> 250.42687 | H18: =H16-H17 -> 266.35249 | I18: =I16-I17 -> 283.23364
B19: Diluted shares | E19: 100 | F19: =Assumptions!C12 -> 100 | G19: =Assumptions!D12 -> 100 | H19: =Assumptions!E12 -> 100 | I19: =Assumptions!F12 -> 100
B20: Diluted EPS | E20: =E18/E19 -> 2.0625 | F20: =IFERROR(F18/F19,"-") -> 2.330625 | G20: =IFERROR(G18/G19,"-") -> 2.5042688 | H20: =IFERROR(H18/H19,"-") -> 2.6635249 | I20: =IFERROR(I18/I19,"-") -> 2.8323364

Sheet BS
B2: Balance Sheet ($mm)
B4: Line item | C4: FY-1A | D4: FY0A | E4: FY1E | F4: FY2E | G4: FY3E
B5: Cash & equivalents | D5: 180
B6: Accounts receivable | D6: 140
B7: Inventory | D7: 95
B8: Total current assets | C8: =C5+C6+C7 -> 0 | D8: =D5+D6+D7 -> 415 | E8: =E5+E6+E7 -> 0 | F8: =F5+F6+F7 -> 0 | G8: =G5+G6+G7 -> 0
B9: PP&E net | D9: 420
B10: Goodwill & intangibles | D10: 60
B11: Total assets | C11: =C8+C9+C10 -> 0 | D11: =D8+D9+D10 -> 895 | E11: =E8+E9+E10 -> 0 | F11: =F8+F9+F10 -> 0 | G11: =G8+G9+G10 -> 0
B12: Accounts payable | D12: 110
B13: Debt (current) | D13: 15
B14: Total current liabilities | C14: =C12+C13 -> 0 | D14: =D12+D13 -> 125 | E14: =E12+E13 -> 0 | F14: =F12+F13 -> 0 | G14: =G12+G13 -> 0
B15: Long-term debt | D15: 180
B16: Total liabilities | C16: =C14+C15 -> 0 | D16: =D14+D15 -> 305 | E16: =E14+E15 -> 0 | F16: =F14+F15 -> 0 | G16: =G14+G15 -> 0
B17: Total equity | D17: =D11-D16 -> 590
B19: Balance check (Total assets - Total liabilities - Total equity, should = 0) | C19: =C11-C16-C17 -> 0 | D19: =D11-D16-D17 -> 0 | E19: =E11-E16-E17 -> 0 | F19: =F11-F16-F17 -> 0 | G19: =G11-G16-G17 -> 0

Sheet CF
B2: Cash Flow ($mm)
B4: Line item | C4: FY-1A | D4: FY0A | E4: FY1E | F4: FY2E | G4: FY3E
B5: Net income | D5: =IS!E18 -> 206.25 | E5: =IS!F18 -> 233.0625 | F5: =IS!G18 -> 250.42687 | G5: =IS!H18 -> 266.35249
B6: + D&A | D6: 45 | E6: =IS!F13 -> 36.45 | F6: =IS!G13 -> 39.0015 | G6: =IS!H13 -> 41.34159
B7: +/- Change in NWC | D7: -12
B8: Cash flow from operations | C8: =C5+C6+C7 -> 0 | D8: =D5+D6+D7 -> 239.25 | E8: =E5+E6+E7 -> 269.5125 | F8: =F5+F6+F7 -> 289.42838 | G8: =G5+G6+G7 -> 307.69408
B9: Capex | D9: -45
B10: Free cash flow | C10: =C8+C9 -> 0 | D10: =D8+D9 -> 194.25 | E10: =E8+E9 -> 269.5125 | F10: =F8+F9 -> 289.42838 | G10: =G8+G9 -> 307.69408
B11: Debt issuance/(repayment) | D11: -10
B12: Dividends/buybacks | D12: -20
B13: Net change in cash | C13: =C10+C11+C12 -> 0 | D13: =D10+D11+D12 -> 164.25 | E13: =E10+E11+E12 -> 269.5125 | F13: =F10+F11+F12 -> 289.42838 | G13: =G10+G11+G12 -> 307.69408

Sheet DCF
B2: DCF Valuation
C4: FY1E | D4: FY2E | E4: FY3E | F4: FY4E | G4: FY5E | H4: Key outputs
B5: Unlevered FCF | C5: =IS!F14*(1-Assumptions!C8)+IS!F13-IS!F5*Assumptions!C10 -> 235.9125 | D5: =IS!G14*(1-Assumptions!D8)+IS!G13-IS!G5*Assumptions!D10 -> 252.42638 | E5: =IS!H14*(1-Assumptions!E8)+IS!H13-IS!H5*Assumptions!E10 -> 267.57196 | F5: =IS!I14*(1-Assumptions!F8)+IS!I13-IS!I5*Assumptions!F10 -> 283.62627 | G5: =F5*(1+Assumptions!G5) -> 297.80759 | H5: WACC | I5: 0.095
B6: Discount factor | C6: =1/(1+$I$5)^(1) -> 0.91324201 | D6: =1/(1+$I$5)^(2) -> 0.83401097 | E6: =1/(1+$I$5)^(3) -> 0.76165385 | F6: =1/(1+$I$5)^(4) -> 0.69557429 | G6: =1/(1+$I$5)^(5) -> 0.63522767 | H6: Terminal growth | I6: 0.025
B7: PV of FCF | C7: =C5*C6 -> 215.44521 | D7: =D5*D6 -> 210.52637 | E7: =E5*E6 -> 203.79721 | F7: =F5*F6 -> 197.28315 | G7: =G5*G6 -> 189.17562 | H7: Terminal value | I7: =G5*(1+I6)/(I5-I6) -> 4360.754
H8: PV of terminal value | I8: =I7*G6 -> 2770.0716
H9: Sum PV of FCF | I9: =SUM(C7:G7) -> 1016.2275
H10: Enterprise value | I10: =I8+I9 -> 3786.2991
H11: Less: net debt | I11: 15
H12: Equity value | I12: =I10-I11 -> 3771.2991
H13: Diluted shares (mm) | I13: 100
H14: Implied value/share | I14: =I12/I13 -> 37.712991

Sheet Comps
B2: Comparable Companies
B4: Ticker | C4: Price | D4: Mkt Cap | E4: EV | F4: EV/Rev | G4: EV/EBITDA | H4: P/E
B5: PEER1 | C5: 42.1 | D5: 4200 | E5: 4550 | F5: 3.1 | G5: 11.5 | H5: 18.2
B6: PEER2 | C6: 67.8 | D6: 6780 | E6: 7100 | F6: 2.8 | G6: 10.2 | H6: 16.5
B7: PEER3 | C7: 28.5 | D7: 2850 | E7: 3050 | F7: 2.5 | G7: 9.8 | H7: 15.1
B8: PEER4 | C8: 95.4 | D8: 9540 | E8: 10100 | F8: 3.4 | G8: 12.8 | H8: 21
B9: [TICKER] | C9: 0 | D9: 0 | E9: 0 | F9: 0 | G9: 0 | H9: 0
B10: [TICKER] | C10: 0 | D10: 0 | E10: 0 | F10: 0 | G10: 0 | H10: 0
B11: [TICKER] | C11: 0 | D11: 0 | E11: 0 | F11: 0 | G11: 0 | H11: 0
B13: Median | C13: =MEDIAN(C5:C12) -> 28.5 | D13: =MEDIAN(D5:D12) -> 2850 | E13: =MEDIAN(E5:E12) -> 3050 | F13: =MEDIAN(F5:F12) -> 2.5 | G13: =MEDIAN(G5:G12) -> 9.8 | H13: =MEDIAN(H5:H12) -> 15.1

Sheet Sensitivity
B2: Sensitivity — Implied Value/Share
B4: WACC \ Term. growth | C4: 0.015 | D4: 0.02 | E4: 0.025 | F4: 0.03 | G4: 0.035
B5: 0.08 | C5: [data table — Excel What-If Analysis] | D5: [data table — Excel What-If Analysis] | E5: [data table — Excel What-If Analysis] | F5: [data table — Excel What-If Analysis] | G5: [data table — Excel What-If Analysis]
B6: 0.09 | C6: [data table — Excel What-If Analysis] | D6: [data table — Excel What-If Analysis] | E6: [data table — Excel What-If Analysis] | F6: [data table — Excel What-If Analysis] | G6: [data table — Excel What-If Analysis]
B7: 0.1 | C7: [data table — Excel What-If Analysis] | D7: [data table — Excel What-If Analysis] | E7: [data table — Excel What-If Analysis] | F7: [data table — Excel What-If Analysis] | G7: [data table — Excel What-If Analysis]
B8: 0.11 | C8: [data table — Excel What-If Analysis] | D8: [data table — Excel What-If Analysis] | E8: [data table — Excel What-If Analysis] | F8: [data table — Excel What-If Analysis] | G8: [data table — Excel What-If Analysis]
B9: 0.12 | C9: [data table — Excel What-If Analysis] | D9: [data table — Excel What-If Analysis] | E9: [data table — Excel What-If Analysis] | F9: [data table — Excel What-If Analysis] | G9: [data table — Excel What-If Analysis]

Sheet RefreshLog
B2: Refresh Log
B4: Date | C4: Trigger | D4: What changed | E4: Reviewer notes | F4: Next check
B5: 2026-06-01 | C5: Initial build | D5: Instance created from template; FY0A actuals entered from illustrative source data. | E5: Self-reviewed against margin assumptions | F5: 2026-07-01
B6: 2026-07-01 | C6: Monthly review | D6: No material change to assumptions; rolled Cover 'Last refreshed' date. | E6: Checked DCF output still in a sane range vs. comps | F6: 2026-08-01
B7: 2026-08-01 | C7: Manual review | D7: Tightened opex% assumption from 25% to 24% on illustrative cost-discipline thesis update. | E7: Re-verified recalc clean, EPS trend still monotonic | F7: 2026-11-05 (next earnings)
