Workbook

Sheet Cover
B2: [BORROWER] — Private Credit / Debt Finance Model
B4: Borrower / issuer: | C4: [fill in]
B5: Facility type: | C5: [term loan B / unitranche / revolver / notes]
B6: Last refreshed: | C6: [date]
B7: Next covenant test date: | C7: [date]
B8: Refresh cadence: | C8: Weekly

Sheet Assumptions
B2: Facility Assumptions
B4: Facility
B5: Facility size / committed amount ($) | C5: 0
B6: Amount drawn ($) | C6: 0
B7: Base rate (e.g. SOFR) % | C7: 0.05
B8: Spread (%) | C8: 0.045
B9: OID (price at issue, per 100) | C9: 99
B10: Maturity (yrs) | C10: 7
B11: Mandatory amortization (% of face / yr) | C11: 0.01
B13: Borrower financials
B14: EBITDA ($) | C14: 0
B15: Cash flow available for debt service (CFADS, $) | C15: 0
B18: Derived
B19: All-in interest rate (base + spread) | C19: =C7+C8 -> 0.095
B20: Annual interest expense ($) | C20: =C6*C19 -> 0
B21: Total debt ($, = drawn amount) | C21: =C6 -> 0
B23: Excess Cash Flow (ECF) Sweep Step-Down Grid | D23: Standard leveraged-loan credit-agreement provision: the sweep % of excess cash flow ratchets down as leverage falls, so a borrower keeps more cash once it's delevered.
B24: Tier | C24: Leverage > | D24: Sweep % of ECF
B25: Tier 1 | C25: 4 | D25: 0.75
B26: Tier 2 | C26: 3 | D26: 0.5
B27: Tier 3 | C27: 2 | D27: 0.25
B28: Below Tier 3 threshold | D28: 0

Sheet Covenants
B2: Covenant Headroom
B4: Covenant | C4: Threshold | D4: Actual | E4: Headroom | F4: Note
B5: Max leverage (Total Debt / EBITDA) | C5: 5 | D5: =IFERROR(Assumptions!C21/Assumptions!C14,"-") -> - | E5: =IFERROR(C5-D5,"-") -> - | F5: Lower actual is better — headroom = covenant minus actual
B6: Min interest coverage (EBITDA / Interest) | C6: 2.5 | D6: =IFERROR(Assumptions!C14/Assumptions!C20,"-") -> - | E6: =IFERROR(D6-C6,"-") -> - | F6: Higher actual is better — headroom = actual minus covenant
B7: Min DSCR (CFADS / Debt Service) | C7: 1.2 | D7: =IFERROR(Assumptions!C15/(Assumptions!C6*Assumptions!C11+Assumptions!C20),"-") -> - | E7: =IFERROR(D7-C7,"-") -> - | F7: Debt service = mandatory amort + interest
B9: Status
B10: Leverage covenant | C10: =IF(NOT(ISNUMBER(D5)),"-",IF(D5<=C5,"PASS","BREACH")) -> -
B11: Interest coverage covenant | C11: =IF(NOT(ISNUMBER(D6)),"-",IF(D6>=C6,"PASS","BREACH")) -> -
B12: DSCR covenant | C12: =IF(NOT(ISNUMBER(D7)),"-",IF(D7>=C7,"PASS","BREACH")) -> -

Sheet Debt Schedule
B2: Debt Schedule
B3: Interest and the ECF sweep tier both key off the BEGINNING-of-period balance — never the period's own ending balance — so nothing here is circular.
C5: Yr0 | D5: Yr1 | E5: Yr2 | F5: Yr3 | G5: Yr4 | H5: Yr5
B6: Beginning balance | C6: =Assumptions!C6 -> 0 | D6: =C12 -> 0 | E6: =D12 -> 0 | F6: =E12 -> 0 | G6: =F12 -> 0 | H6: =G12 -> 0
B7: Mandatory amortization | C7: =Assumptions!$C$6*Assumptions!$C$11 -> 0 | D7: =Assumptions!$C$6*Assumptions!$C$11 -> 0 | E7: =Assumptions!$C$6*Assumptions!$C$11 -> 0 | F7: =Assumptions!$C$6*Assumptions!$C$11 -> 0 | G7: =Assumptions!$C$6*Assumptions!$C$11 -> 0 | H7: =Assumptions!$C$6*Assumptions!$C$11 -> 0
B8: Beginning-of-period leverage (for ECF tier) | C8: =IFERROR(C6/Assumptions!$C$14,"-") -> - | D8: =IFERROR(D6/Assumptions!$C$14,"-") -> - | E8: =IFERROR(E6/Assumptions!$C$14,"-") -> - | F8: =IFERROR(F6/Assumptions!$C$14,"-") -> - | G8: =IFERROR(G6/Assumptions!$C$14,"-") -> - | H8: =IFERROR(H6/Assumptions!$C$14,"-") -> -
B9: ECF sweep % (step-down grid) | C9: =IF(NOT(ISNUMBER(C8)),0,IF(C8>Assumptions!$C$25,Assumptions!$D$25,IF(C8>Assumptions!$C$26,Assumptions!$D$26,IF(C8>Assumptions!$C$27,Assumptions!$D$27,Assumptions!$D$28)))) -> 0 | D9: =IF(NOT(ISNUMBER(D8)),0,IF(D8>Assumptions!$C$25,Assumptions!$D$25,IF(D8>Assumptions!$C$26,Assumptions!$D$26,IF(D8>Assumptions!$C$27,Assumptions!$D$27,Assumptions!$D$28)))) -> 0 | E9: =IF(NOT(ISNUMBER(E8)),0,IF(E8>Assumptions!$C$25,Assumptions!$D$25,IF(E8>Assumptions!$C$26,Assumptions!$D$26,IF(E8>Assumptions!$C$27,Assumptions!$D$27,Assumptions!$D$28)))) -> 0 | F9: =IF(NOT(ISNUMBER(F8)),0,IF(F8>Assumptions!$C$25,Assumptions!$D$25,IF(F8>Assumptions!$C$26,Assumptions!$D$26,IF(F8>Assumptions!$C$27,Assumptions!$D$27,Assumptions!$D$28)))) -> 0 | G9: =IF(NOT(ISNUMBER(G8)),0,IF(G8>Assumptions!$C$25,Assumptions!$D$25,IF(G8>Assumptions!$C$26,Assumptions!$D$26,IF(G8>Assumptions!$C$27,Assumptions!$D$27,Assumptions!$D$28)))) -> 0 | H9: =IF(NOT(ISNUMBER(H8)),0,IF(H8>Assumptions!$C$25,Assumptions!$D$25,IF(H8>Assumptions!$C$26,Assumptions!$D$26,IF(H8>Assumptions!$C$27,Assumptions!$D$27,Assumptions!$D$28)))) -> 0
B10: Interest expense (all-in rate x beginning balance) | C10: =C6*Assumptions!$C$19 -> 0 | D10: =D6*Assumptions!$C$19 -> 0 | E10: =E6*Assumptions!$C$19 -> 0 | F10: =F6*Assumptions!$C$19 -> 0 | G10: =G6*Assumptions!$C$19 -> 0 | H10: =H6*Assumptions!$C$19 -> 0
B11: Cash sweep (Excess Cash Flow: CFADS less scheduled debt service, x tier %) | C11: =MAX(Assumptions!$C$15-C10-C7,0)*C9 -> 0 | D11: =MAX(Assumptions!$C$15-D10-D7,0)*D9 -> 0 | E11: =MAX(Assumptions!$C$15-E10-E7,0)*E9 -> 0 | F11: =MAX(Assumptions!$C$15-F10-F7,0)*F9 -> 0 | G11: =MAX(Assumptions!$C$15-G10-G7,0)*G9 -> 0 | H11: =MAX(Assumptions!$C$15-H10-H7,0)*H9 -> 0
B12: Ending balance | C12: =C6-C7-C11 -> 0 | D12: =D6-D7-D11 -> 0 | E12: =E6-E7-E11 -> 0 | F12: =F6-F7-F11 -> 0 | G12: =G6-G7-G11 -> 0 | H12: =H6-H7-H11 -> 0
B14: Leverage (ending debt / EBITDA) | C14: =IFERROR(C12/Assumptions!$C$14,"-") -> - | D14: =IFERROR(D12/Assumptions!$C$14,"-") -> - | E14: =IFERROR(E12/Assumptions!$C$14,"-") -> - | F14: =IFERROR(F12/Assumptions!$C$14,"-") -> - | G14: =IFERROR(G12/Assumptions!$C$14,"-") -> - | H14: =IFERROR(H12/Assumptions!$C$14,"-") -> -

Sheet Yield & Spread
B2: Lender Yield (incl. OID)
B4: Coupon rate (base + spread, %) | C4: =Assumptions!C19 -> 0.095
B5: Issue price (per 100) | C5: =Assumptions!C9 -> 99
B6: Maturity (yrs) | C6: =Assumptions!C10 -> 7
B8: Approx. yield-to-maturity | C8: =IFERROR((C4*100+(100-C5)/C6)/((100+C5)/2),"-") -> 0.096913137 | D8: Standard bond-math approximation: (Coupon$+(100-Price)/n)/((100+Price)/2). At par (Price=100) this collapses to the coupon rate exactly — sanity check.

Sheet Sources
B2: Sources
B3: What each material assumption or convention in this model comes from.
B5: Assumption / convention | C5: Source | D5: As of | E5: Note
B6: ECF sweep step-down grid (75%/50%/25%/0% by leverage tier) | C6: Standard leveraged-loan credit-agreement provision | D6: Standard practice | E6: Illustrative tier thresholds/percentages — not any specific credit agreement's actual terms
B7: Covenant thresholds (5.0x leverage, 2.5x interest coverage, 1.2x DSCR) | C7: [fill in — actual credit agreement] | D7: [fill in] | E7: Placeholder defaults; replace with the specific facility's real covenant levels before use
B8: Approximate YTM: (coupon$+(100-price)/n)/((100+price)/2) | C8: Standard bond-math approximation for yield including OID | D8: Standard practice | E8: Approximation, not an exact IRR solve — collapses to the coupon rate exactly at par (Price=100), the built-in sanity check
B9: Interest computed off beginning-of-period balance only (not average) | C9: Modeling convention used throughout this repo to avoid circular references between interest and the ECF sweep | D9: Standard practice | E9: Slightly understates true average-balance interest expense when the balance amortizes or sweeps within the period

Sheet Checks
B2: Checks
B3: Live reconciliation identities -- independent of the model's own formulas, must tie.
B5: Check | C5: Result | D5: Passes when
B6: Ending balance ties: beginning - amort - sweep = ending (Yr5) | C6: ='Debt Schedule'!H12-('Debt Schedule'!H6-'Debt Schedule'!H7-'Debt Schedule'!H11) -> 0 | D6: 0 (exact)
B7: Roll-forward ties: next period's beginning = this period's ending (Yr0->Yr1) | C7: ='Debt Schedule'!D6-'Debt Schedule'!C12 -> 0 | D7: 0 (exact)
B8: Total debt (Assumptions) ties to Debt Schedule Yr0 beginning balance | C8: =Assumptions!C21-'Debt Schedule'!C6 -> 0 | D8: 0 (exact)
B9: ECF sweep never negative (MAX floor holds across the full schedule) | C9: =IF(MIN('Debt Schedule'!C11:H11)>=0,TRUE(),FALSE()) -> TRUE | D9: TRUE

Sheet RefreshLog
B2: Refresh Log
B4: Date | C4: Trigger | D4: What changed | E4: Reviewer notes | F4: Next check
