Workbook

Sheet Cover
B2: [ISSUER] — Public Finance Model
B4: Issuer: | C4: [fill in — sovereign, state, muni, agency]
B5: Instrument: | C5: [general obligation / revenue bond / sovereign note]
B6: Last refreshed: | C6: [date]
B7: Next payment / issuance date: | C7: [date]
B8: Refresh cadence: | C8: Weekly
B9: Scenario (Base/Stress): | C9: Base

Sheet Debt Sustainability
B2: Debt Sustainability Analysis (DSA)
B4: Inputs
B5: Total public debt / GDP (or Debt/Revenue) ratio (%) | C5: 0.6
B6: Effective interest rate on debt, r (%) | C6: 0.05
B7: Nominal GDP (or revenue base) growth rate, g (%) | C7: 0.02
B8: Current primary balance (% of GDP; surplus positive) | C8: 0
B10: Outputs
B11: Debt-stabilizing primary balance, pb* = (r-g)/(1+g) x debt ratio | C11: =IFERROR((C6-C7)/(1+C7)*C5,"-") -> 0.017647059 | D11: Standard IMF/DSA formula. If r>g, debt ratio is explosive unless the primary balance is at least this large.
B12: Primary balance gap (current minus required) | C12: =IFERROR(C8-C11,"-") -> -0.017647059 | D12: Negative = running a bigger deficit than needed to stabilize the debt ratio; ratio will rise.
B13: Debt trajectory | C13: =IFERROR(IF(C8>=C11,"STABILIZING/FALLING","RISING"),"-") -> RISING | D13: Rule of thumb only — ignores stock-flow adjustments, FX-denominated debt, contingent liabilities.

Sheet Revenue Bond Coverage
B2: Revenue Bond Coverage
B4: Inputs
B5: Gross pledged revenue ($) | C5: 0
B6: Operating & maintenance expense ($) | C6: 0
B7: Senior debt service — P&I ($) | C7: 0
B8: Subordinate debt service — P&I ($) | C8: 0
B10: Outputs
B11: Net revenue available for debt service | C11: =IFERROR(C5-C6,"-") -> 0
B12: Senior DSCR (Net revenue / Senior debt service) | C12: =IFERROR(C11/C7,"-") -> -
B13: All-in DSCR (Net revenue / Total debt service) | C13: =IFERROR(C11/(C7+C8),"-") -> -
B15: Additional Bonds Test covenant
B16: ABT minimum senior DSCR covenant | C16: 1.25
B17: Current-period headroom (actual minus covenant) | C17: =IFERROR(C12-C16,"-") -> -
B18: See the 'Additional Bonds Test' sheet for the forward-looking test on a proposed new issuance

Sheet Additional Bonds Test
B2: Additional Bonds Test — Proposed New Issuance
B3: A static current-DSCR-vs-covenant check answers 'are we compliant today.' An ABT answers a different question: 'if we issue $X of new parity debt, do we STILL clear covenant' — the actual gate that decides whether a revenue-bond issuer can borrow more.
B5: Proposed New Issuance
B6: New par amount ($) | C6: 20000000
B7: Coupon rate on new bonds (%) | C7: 0.045
B8: Term of new bonds (years) | C8: 20
B9: New bond level annual debt service (P&I) | C9: =IFERROR(-PMT(C7,C8,C6),"-") -> 1537522.9 | D9: Assumes current-interest, level-debt-service structuring (the standard muni convention) — Excel's native PMT, not a capital-appreciation or non-level schedule.
B11: Existing Debt Service & Net Revenue
B12: Existing senior debt service ($) | C12: ='Revenue Bond Coverage'!C7 -> 0
B13: Net revenue available for debt service ($) | C13: ='Revenue Bond Coverage'!C11 -> 0
B14: ABT minimum senior DSCR covenant | C14: ='Revenue Bond Coverage'!C16 -> 1.25
B16: Historical (Look-Back) Test
B17: Pro-forma total senior debt service ($) = existing + new | C17: =C12+C9 -> 1537522.9
B18: Pro-forma senior DSCR | C18: =IFERROR(C13/C17,"-") -> 0
B19: Headroom (pro-forma DSCR minus covenant) | C19: =IFERROR(C18-C14,"-") -> -1.25
B20: Historical test result | C20: =IF(NOT(ISNUMBER(C18)),"-",IF(C18>=C14,"PASS","FAIL")) -> FAIL
B22: Projected (Look-Forward) Test
B23: Active scenario (from Cover) | C23: =Cover!C9 -> Base
B24: Revenue growth rate — Base (%) | C24: 0.03
B25: Revenue growth rate — Stress (%) | C25: -0.02
B26: O&M growth rate — Base (%) | C26: 0.025
B27: O&M growth rate — Stress (%) | C27: 0.05
B28: Active revenue growth rate | C28: =IF(Cover!$C$9="Stress",C25,C24) -> 0.03
B29: Active O&M growth rate | C29: =IF(Cover!$C$9="Stress",C27,C26) -> 0.025
B31: Year | C31: Gross Revenue | D31: O&M | E31: Net Revenue | F31: Pro-forma Senior DS | G31: Pro-forma DSCR | H31: Pass/Fail
B32: Year 1 | C32: ='Revenue Bond Coverage'!$C$5*(1+$C$28) -> 0 | D32: ='Revenue Bond Coverage'!$C$6*(1+$C$29) -> 0 | E32: =C32-D32 -> 0 | F32: =$C$17 -> 1537522.9 | G32: =IFERROR(E32/F32,"-") -> 0 | H32: =IF(G32>=$C$14,"PASS","FAIL") -> FAIL
B33: Year 2 | C33: =C32*(1+$C$28) -> 0 | D33: =D32*(1+$C$29) -> 0 | E33: =C33-D33 -> 0 | F33: =$C$17 -> 1537522.9 | G33: =IFERROR(E33/F33,"-") -> 0 | H33: =IF(G33>=$C$14,"PASS","FAIL") -> FAIL
B34: Year 3 | C34: =C33*(1+$C$28) -> 0 | D34: =D33*(1+$C$29) -> 0 | E34: =C34-D34 -> 0 | F34: =$C$17 -> 1537522.9 | G34: =IFERROR(E34/F34,"-") -> 0 | H34: =IF(G34>=$C$14,"PASS","FAIL") -> FAIL
B35: Year 4 | C35: =C34*(1+$C$28) -> 0 | D35: =D34*(1+$C$29) -> 0 | E35: =C35-D35 -> 0 | F35: =$C$17 -> 1537522.9 | G35: =IFERROR(E35/F35,"-") -> 0 | H35: =IF(G35>=$C$14,"PASS","FAIL") -> FAIL
B36: Year 5 | C36: =C35*(1+$C$28) -> 0 | D36: =D35*(1+$C$29) -> 0 | E36: =C36-D36 -> 0 | F36: =$C$17 -> 1537522.9 | G36: =IFERROR(E36/F36,"-") -> 0 | H36: =IF(G36>=$C$14,"PASS","FAIL") -> FAIL
B38: Minimum projected DSCR (5-yr window) | C38: =MIN(G32:G36) -> 0
B39: Year of minimum | C39: =INDEX(B32:B36,MATCH(C38,G32:G36,0)) -> Year 1
B40: Projected test result | C40: =IF(C38>=C14,"PASS — all 5 years clear covenant","FAIL — covenant breached in "&C39) -> FAIL — covenant breached in Year 1
B42: Indentures typically require passing the historical OR the projected test (not always both) before additional parity debt may be issued — confirm which applies for a specific issuer's indenture; see model_card.md.

Sheet Sources
B2: Sources
B3: What each material assumption or convention in this model comes from.
B5: Assumption / convention | C5: Source | D5: As of | E5: Note
B6: Debt-stabilizing primary balance, pb* = (r-g)/(1+g) x debt ratio | C6: IMF Debt Sustainability Analysis (DSA) framework | D6: Standard practice | E6: Public-domain IMF methodology, not issuer-specific
B7: Additional Bonds Test: historical + projected look-forward tests | C7: Typical municipal revenue-bond indenture additional-parity-debt covenant | D7: Standard practice | E7: Actual indenture language varies by issuer; implements the common historical-or-projected pattern
B8: New-issuance level debt service (PMT amortization) | C8: Standard level-debt-service muni bond structuring convention | D8: Standard practice | E8: Current-interest, level P&I only — no capital-appreciation or non-level schedules
B9: ABT minimum senior DSCR covenant (1.25x default) | C9: [fill in — issuer's actual bond indenture] | D9: [fill in] | E9: Placeholder default; replace with the specific indenture's real covenant level before use

Sheet Checks
B2: Checks
B3: Live reconciliation identities -- independent of the model's own formulas, must tie.
B5: Check | C5: Result | D5: Passes when
B6: Net revenue ties: Gross revenue - O&M = Net revenue | C6: ='Revenue Bond Coverage'!C11-('Revenue Bond Coverage'!C5-'Revenue Bond Coverage'!C6) -> 0 | D6: 0 (exact)
B7: Pro-forma Yr1 debt service ties: existing + new = pro forma | C7: ='Additional Bonds Test'!C17-('Additional Bonds Test'!C12+'Additional Bonds Test'!C9) -> 0 | D7: 0 (exact)
B8: New-bond PMT reproduces closed-form level-annuity payment | C8: ='Additional Bonds Test'!C9-('Additional Bonds Test'!C6*'Additional Bonds Test'!C7/(1-(1+'Additional Bonds Test'!C7)^-'Additional Bonds Test'!C8)) -> 0 | D8: ~0 (native PMT matches closed-form annuity formula)
B9: DSA trajectory label matches sign of primary-balance gap | C9: =IF('Debt Sustainability'!C12>=0,"STABILIZING/FALLING","RISING")='Debt Sustainability'!C13 -> TRUE | D9: TRUE

Sheet RefreshLog
B2: Refresh Log
B4: Date | C4: Trigger | D4: What changed | E4: Reviewer notes | F4: Next check
