Workbook

Sheet Cover
B2: [TARGET] — LBO Model
B4: Sponsor: | C4: [Example Sponsor] Industrial Capital
B5: Deal type: | C5: LBO / carve-out
B6: Last refreshed: | C6: 2026-08-04
B7: Next covenant/refinancing date: | C7: 2027-02-04
B8: Entry date: | C8: 2026-01-15
B9: Hold period (yrs): | C9: 5
B10: Refresh cadence: | C10: Weekly
B11: Active scenario (Base or Downside): | C11: Base

Sheet Sources & Uses
B2: Sources & Uses
B4: Sources | E4: Uses
B5: Revolver (undrawn at close) | C5: 0 | E5: Purchase of equity (at entry mult.) | F5: 300
B6: Term Loan A | C6: 100 | E6: Refinance existing debt | F6: 0
B7: Term Loan B | C7: 80 | E7: Transaction fees | F7: 5
B8: Senior Notes | C8: 0 | E8: Financing fees | F8: 3
B9: Sponsor equity | C9: 115 | E9: Cash to balance sheet | F9: 2
B10: Management rollover | C10: 15 | E10: Total uses | F10: =SUM(F5:F9) -> 310
B11: Total sources | C11: =SUM(C5:C10) -> 310
B13: Check (sources = uses): | C13: =C11-F10 -> 0

Sheet Debt Schedule
B2: Debt Schedule — Revolver / TLA / TLB (with cash sweep)
C4: Yr0 | D4: Yr1 | E4: Yr2 | F4: Yr3 | G4: Yr4 | H4: Yr5 | J4: Assumptions | K4: Base | L4: Downside | M4: Active
B5: EBITDA | C5: =Returns!C5 -> 40 | D5: =C5*(1+$M$5) -> 41.6 | E5: =D5*(1+$M$5) -> 43.264 | F5: =E5*(1+$M$5) -> 44.99456 | G5: =F5*(1+$M$5) -> 46.794342 | H5: =G5*(1+$M$5) -> 48.666116 | J5: Entry EBITDA growth (%/yr) | K5: 0.04 | L5: -0.12 | M5: =IF(Cover!$C$11="Downside",L5,K5) -> 0.04
B6: Cash flow available for debt service (FCF) | C6: =C5*$M$6 -> 14 | D6: =D5*$M$6 -> 14.56 | E6: =E5*$M$6 -> 15.1424 | F6: =F5*$M$6 -> 15.748096 | G6: =G5*$M$6 -> 16.37802 | H6: =H5*$M$6 -> 17.033141 | J6: FCF conversion (FCF / EBITDA, %) | K6: 0.35 | L6: 0.15 | M6: =IF(Cover!$C$11="Downside",L6,K6) -> 0.35
J7: TLA mandatory amort (% of original/yr) | K7: 0.06 | L7: 0.06 | M7: =IF(Cover!$C$11="Downside",L7,K7) -> 0.06
B8: Revolving Credit Facility | J8: TLA interest rate (%) | K8: 0.075 | L8: 0.095 | M8: =IF(Cover!$C$11="Downside",L8,K8) -> 0.075
B9: Beginning balance | C9: =$M$16 -> 0 | D9: =C13 -> 8.3 | E9: =D13 -> 16.2155 | F9: =E13 -> 23.691418 | G9: =F13 -> 30 | H9: =G13 -> 30 | J9: TLB mandatory amort (% of original/yr) | K9: 0.01 | L9: 0.01 | M9: =IF(Cover!$C$11="Downside",L9,K9) -> 0.01
B10: Interest expense (rate x beginning balance) | C10: =C9*$M$13 -> 0 | D10: =D9*$M$13 -> 0.7055 | E10: =E9*$M$13 -> 1.3783175 | F10: =F9*$M$13 -> 2.0137705 | G10: =G9*$M$13 -> 2.55 | H10: =H9*$M$13 -> 2.55 | J10: TLB interest rate (%) | K10: 0.1 | L10: 0.125 | M10: =IF(Cover!$C$11="Downside",L10,K10) -> 0.1
B11: Cash available for revolver / sweep decisions | C11: =C6-C18-C25-C10-C21-C28 -> -8.3 | D11: =D6-D18-D25-D10-D21-D28 -> -7.9155 | E11: =E6-E18-E25-E10-E21-E28 -> -7.4759175 | F11: =F6-F18-F25-F10-F21-F28 -> -6.9756745 | G11: =G6-G18-G25-G10-G21-G28 -> -6.3519802 | H11: =H6-H18-H25-H10-H21-H28 -> -5.1668594 | J11: Cash sweep (% of excess cash, after revolver) | K11: 0.75 | L11: 0.75 | M11: =IF(Cover!$C$11="Downside",L11,K11) -> 0.75
B12: Draw / (repayment) | C12: =IF(C11<0,MIN(-C11,$M$12-C9),-MIN(C9,MAX(0,C11))) -> 8.3 | D12: =IF(D11<0,MIN(-D11,$M$12-D9),-MIN(D9,MAX(0,D11))) -> 7.9155 | E12: =IF(E11<0,MIN(-E11,$M$12-E9),-MIN(E9,MAX(0,E11))) -> 7.4759175 | F12: =IF(F11<0,MIN(-F11,$M$12-F9),-MIN(F9,MAX(0,F11))) -> 6.3085825 | G12: =IF(G11<0,MIN(-G11,$M$12-G9),-MIN(G9,MAX(0,G11))) -> 0 | H12: =IF(H11<0,MIN(-H11,$M$12-H9),-MIN(H9,MAX(0,H11))) -> 0 | J12: Revolver commitment / capacity ($) | K12: 30 | L12: 30 | M12: =IF(Cover!$C$11="Downside",L12,K12) -> 30
B13: Ending balance | C13: =C9+C12 -> 8.3 | D13: =D9+D12 -> 16.2155 | E13: =E9+E12 -> 23.691418 | F13: =F9+F12 -> 30 | G13: =G9+G12 -> 30 | H13: =H9+H12 -> 30 | J13: Revolver interest rate (%, on drawn balance) | K13: 0.085 | L13: 0.105 | M13: =IF(Cover!$C$11="Downside",L13,K13) -> 0.085
B14: Excess cash remaining for term loan sweep | C14: =MAX(0,MAX(0,C11)-C9) -> 0 | D14: =MAX(0,MAX(0,D11)-D9) -> 0 | E14: =MAX(0,MAX(0,E11)-E9) -> 0 | F14: =MAX(0,MAX(0,F11)-F9) -> 0 | G14: =MAX(0,MAX(0,G11)-G9) -> 0 | H14: =MAX(0,MAX(0,H11)-H9) -> 0 | J14: Original TLA balance (Yr0, $) | M14: ='Sources & Uses'!C6 -> 100
J15: Original TLB balance (Yr0, $) | M15: ='Sources & Uses'!C7 -> 80
B16: Term Loan A (senior, amortizing) | J16: Revolver drawn at close ($) | M16: ='Sources & Uses'!C5 -> 0
B17: Beginning balance | C17: =$M$14 -> 100 | D17: =C20 -> 94 | E17: =D20 -> 88 | F17: =E20 -> 82 | G17: =F20 -> 76 | H17: =G20 -> 70
B18: Mandatory amortization | C18: =MIN($M$14*$M$7,C17) -> 6 | D18: =MIN($M$14*$M$7,D17) -> 6 | E18: =MIN($M$14*$M$7,E17) -> 6 | F18: =MIN($M$14*$M$7,F17) -> 6 | G18: =MIN($M$14*$M$7,G17) -> 6 | H18: =MIN($M$14*$M$7,H17) -> 6 | J18: Deal terms (rows 14-16) don't vary by scenario, so they skip the
B19: Cash sweep (after revolver fully repaid) | C19: =MIN($M$11*C14,C17-C18) -> 0 | D19: =MIN($M$11*D14,D17-D18) -> 0 | E19: =MIN($M$11*E14,E17-E18) -> 0 | F19: =MIN($M$11*F14,F17-F18) -> 0 | G19: =MIN($M$11*G14,G17-G18) -> 0 | H19: =MIN($M$11*H14,H17-H18) -> 0 | J19: Base/Downside split and go straight in the Active column. Revolver
B20: Ending balance | C20: =C17-C18-C19 -> 94 | D20: =D17-D18-D19 -> 88 | E20: =E17-E18-E19 -> 82 | F20: =F17-F18-F19 -> 76 | G20: =G17-G18-G19 -> 70 | H20: =H17-H18-H19 -> 64 | J20: commitment (M12) is total facility SIZE available to draw against,
B21: Interest expense (rate x beginning balance) | C21: =C17*$M$8 -> 7.5 | D21: =D17*$M$8 -> 7.05 | E21: =E17*$M$8 -> 6.6 | F21: =F17*$M$8 -> 6.15 | G21: =G17*$M$8 -> 5.7 | H21: =H17*$M$8 -> 5.25 | J21: separate from the 'drawn at close' amount (M16, typically 0).
B23: Term Loan B (junior)
B24: Beginning balance | C24: =$M$15 -> 80 | D24: =C27 -> 79.2 | E24: =D27 -> 78.4 | F24: =E27 -> 77.6 | G24: =F27 -> 76.8 | H24: =G27 -> 76
B25: Mandatory amortization | C25: =MIN($M$15*$M$9,C24) -> 0.8 | D25: =MIN($M$15*$M$9,D24) -> 0.8 | E25: =MIN($M$15*$M$9,E24) -> 0.8 | F25: =MIN($M$15*$M$9,F24) -> 0.8 | G25: =MIN($M$15*$M$9,G24) -> 0.8 | H25: =MIN($M$15*$M$9,H24) -> 0.8
B26: Cash sweep (only after TLA fully repaid) | C26: =MIN($M$11*C14-C19,C24-C25) -> 0 | D26: =MIN($M$11*D14-D19,D24-D25) -> 0 | E26: =MIN($M$11*E14-E19,E24-E25) -> 0 | F26: =MIN($M$11*F14-F19,F24-F25) -> 0 | G26: =MIN($M$11*G14-G19,G24-G25) -> 0 | H26: =MIN($M$11*H14-H19,H24-H25) -> 0
B27: Ending balance | C27: =C24-C25-C26 -> 79.2 | D27: =D24-D25-D26 -> 78.4 | E27: =E24-E25-E26 -> 77.6 | F27: =F24-F25-F26 -> 76.8 | G27: =G24-G25-G26 -> 76 | H27: =H24-H25-H26 -> 75.2
B28: Interest expense (rate x beginning balance) | C28: =C24*$M$10 -> 8 | D28: =D24*$M$10 -> 7.92 | E28: =E24*$M$10 -> 7.84 | F28: =F24*$M$10 -> 7.76 | G28: =G24*$M$10 -> 7.68 | H28: =H24*$M$10 -> 7.6
B30: Total debt (end of period) | C30: =C13+C20+C27 -> 181.5 | D30: =D13+D20+D27 -> 182.6155 | E30: =E13+E20+E27 -> 183.29142 | F30: =F13+F20+F27 -> 182.8 | G30: =G13+G20+G27 -> 176 | H30: =H13+H20+H27 -> 169.2
B31: Total interest expense | C31: =C10+C21+C28 -> 15.5 | D31: =D10+D21+D28 -> 15.6755 | E31: =E10+E21+E28 -> 15.818317 | F31: =F10+F21+F28 -> 15.92377 | G31: =G10+G21+G28 -> 15.93 | H31: =H10+H21+H28 -> 15.4
B32: Total debt / EBITDA (leverage) | C32: =IFERROR(C30/C5,"-") -> 4.5375 | D32: =IFERROR(D30/D5,"-") -> 4.3897957 | E32: =IFERROR(E30/E5,"-") -> 4.2365805 | F32: =IFERROR(F30/F5,"-") -> 4.0627134 | G32: =IFERROR(G30/G5,"-") -> 3.7611384 | H32: =IFERROR(H30/H5,"-") -> 3.4767517

Sheet Returns
B2: Returns — IRR / MOIC
B4: Entry
B5: Entry EBITDA | C5: 40
B6: Entry multiple | C6: 7.5
B7: Entry EV | C7: =C5*C6 -> 300
B8: Sponsor equity check | C8: ='Sources & Uses'!C9 -> 115
B10: Exit
B11: Exit EBITDA (Yr5) | C11: ='Debt Schedule'!H5 -> 48.666116 | D11: Base | E11: Downside
B12: Exit multiple (Active) | C12: =IFERROR(IF(Cover!$C$11="Downside",E12,D12),"-") -> 8 | D12: 8 | E12: 6
B13: Exit EV | C13: =C11*C12 -> 389.32893
B14: Less: net debt at exit | C14: ='Debt Schedule'!H30 -> 169.2
B15: Exit equity value | C15: =C13-C14 -> 220.12893
B17: Deal-Level Returns (blended, before management promote)
B18: MOIC (exit equity value / ALL invested equity, sponsor + mgmt) | C18: =IFERROR(C15/(C8+'Sources & Uses'!C10),"-") -> 1.6932995 | D18: Everyone's return before the promote reallocates value from sponsor to management below — not the sponsor's actual net return
B19: Hold period (yrs) | C19: =Cover!C9 -> 5
B20: IRR | C20: =IFERROR(C18^(1/C19)-1,"-") -> 0.11108364
B22: Management Promote / Ratchet
B23: Total sponsor + management invested equity | C23: ='Sources & Uses'!C9+'Sources & Uses'!C10 -> 130
B24: Management rollover % of total equity | C24: =IFERROR('Sources & Uses'!C10/C23,"-") -> 0.11538462
B25: IRR hurdle for promote to kick in | C25: 0.2
B26: Management promote % of value created above hurdle | C26: 0.2
B27: Hurdle equity value (invested equity grown at hurdle IRR) | C27: =IFERROR(C23*(1+C25)^C19,"-") -> 323.4816
B28: Value created above hurdle | C28: =MAX(0,C15-C27) -> 0
B29: Management promote ($) | C29: =C28*C26 -> 0
B30: Management total proceeds (pro-rata rollover + promote) | C30: =IFERROR(C24*C15+C29,"-") -> 25.399492
B31: Sponsor net proceeds (exit equity value less management take) | C31: =IFERROR(C15-C30,"-") -> 194.72944
B32: Sponsor-only MOIC (on sponsor equity, net of promote paid away) | C32: =IFERROR(C31/'Sources & Uses'!C9,"-") -> 1.6932995
B33: Sponsor-only IRR (net of promote paid away) | C33: =IFERROR(C32^(1/C19)-1,"-") -> 0.11108364 | D33: This is the number that actually matters to the sponsor's LPs — the blended IRR above overstates what the fund itself earns once management's promote is paid away

Sheet Sensitivity
B2: Sensitivity — IRR by Entry/Exit Multiple
B4: Entry \ Exit mult. | C4: 7 | D4: 8 | E4: 9 | F4: 10 | G4: 11
B5: 6 | C5: [data table — Excel What-If Analysis] | D5: [data table — Excel What-If Analysis] | E5: [data table — Excel What-If Analysis] | F5: [data table — Excel What-If Analysis] | G5: [data table — Excel What-If Analysis]
B6: 7 | C6: [data table — Excel What-If Analysis] | D6: [data table — Excel What-If Analysis] | E6: [data table — Excel What-If Analysis] | F6: [data table — Excel What-If Analysis] | G6: [data table — Excel What-If Analysis]
B7: 8 | C7: [data table — Excel What-If Analysis] | D7: [data table — Excel What-If Analysis] | E7: [data table — Excel What-If Analysis] | F7: [data table — Excel What-If Analysis] | G7: [data table — Excel What-If Analysis]
B8: 9 | C8: [data table — Excel What-If Analysis] | D8: [data table — Excel What-If Analysis] | E8: [data table — Excel What-If Analysis] | F8: [data table — Excel What-If Analysis] | G8: [data table — Excel What-If Analysis]
B9: 10 | C9: [data table — Excel What-If Analysis] | D9: [data table — Excel What-If Analysis] | E9: [data table — Excel What-If Analysis] | F9: [data table — Excel What-If Analysis] | G9: [data table — Excel What-If Analysis]

Sheet RefreshLog
B2: Refresh Log
B4: Date | C4: Trigger | D4: What changed | E4: Reviewer notes | F4: Next check
