Workbook

Sheet Cover
B2: [FUND] — Asset Management Model
B4: Fund structure: | C4: Hedge fund / PE fund / mutual fund
B5: Vintage / inception: | C5: [date]
B6: Last refreshed: | C6: [date]
B7: Next capital call/distribution: | C7: [date]
B8: Refresh cadence: | C8: Weekly (monthly NAV strike)

Sheet Fund NAV
B2: Fund NAV Build
C4: Period 0 | D4: Period 1 | E4: Period 2 | F4: Period 3
B5: Beginning NAV | C5: 0 | D5: =C10 -> 0 | E5: =D10 -> 0 | F5: =E10 -> 0
B6: + Capital contributions | C6: 0 | D6: 0 | E6: 0 | F6: 0
B7: + Realized/unrealized gains | C7: 0 | D7: 0 | E7: 0 | F7: 0
B8: - Fees & expenses | C8: 0 | D8: 0 | E8: 0 | F8: 0
B9: - Distributions | C9: 0 | D9: 0 | E9: 0 | F9: 0
B10: Ending NAV | C10: =C5+C6+C7-C8-C9 -> 0 | D10: =D5+D6+D7-D8-D9 -> 0 | E10: =E5+E6+E7-E8-E9 -> 0 | F10: =F5+F6+F7-F8-F9 -> 0

Sheet Fee Waterfall
B2: Fee Waterfall — Mgmt Fee + Carry w/ Hurdle
B4: Inputs
B5: Committed capital | C5: 0
B6: Management fee % | C6: 0.02
B7: Preferred return / hurdle % | C7: 0.08
B8: Carry / promote % | C8: 0.2
B9: GP catch-up % | C9: 1
B10: Gross fund profit (this period) | C10: 0
B11: Capital invested (basis for hurdle) | C11: 0
B13: Waterfall
B14: 1. Return of capital | C14: =MIN(C10,C11) -> 0
B15: 2. Preferred return (hurdle) to LPs | C15: =MIN(MAX(C10-C14,0),C11*C7) -> 0
B16: 3. GP catch-up tranche (total, before GP/LP split) | C16: =IF(C9<=C8,0,MIN(MAX(C10-C14-C15,0),C15*C8/(C9-C8))) -> 0 | D16: General catch-up formula for an arbitrary catch-up rate C9 (not hardcoded to 100%): tranche size = pref x carry% / (catch-up% - carry%). At C9=100% this collapses to the standard pref x carry%/(1-carry%) formula.
B17: GP share of catch-up tranche (x catch-up %) | C17: =C16*C9 -> 0
B18: LP share of catch-up tranche (x (1 - catch-up %)) | C18: =C16*(1-C9) -> 0
B19: 4. Remaining profit split (LP/GP per carry%) | C19: =MAX(C10-C14-C15-C16,0) -> 0
B20: GP share of remainder | C20: =C19*C8 -> 0
B21: LP share of remainder | C21: =C19*(1-C8) -> 0
B23: Total GP take (catch-up + carry) | C23: =C17+C20 -> 0
B24: Total LP take | C24: =C14+C15+C18+C21 -> 0
B25: Annual management fee (separate from carry) | C25: =C5*C6 -> 0
B26: GP effective carry % of total profit (sanity check — should trend to C8 as profit grows) | C26: =IFERROR(C23/(C10-C14),"-") -> -

Sheet GP Carry & Clawback
B2: GP Carry & Clawback — Whole-Fund (European) Waterfall
B3: Re-runs the SAME waterfall as the Fee Waterfall tab, but cumulatively through each period rather than once. That's what a whole-fund/European waterfall actually is: carry earned to date is always a function of CUMULATIVE fund performance, so a later markdown can make previously-paid carry excessive -- a clawback obligation -- which a single-period calc can never show.
C5: Period 0 | D5: Period 1 | E5: Period 2 | F5: Period 3
B6: Cumulative capital contributed | C6: =SUM('Fund NAV'!$C$6:C6) -> 0 | D6: =SUM('Fund NAV'!$C$6:D6) -> 0 | E6: =SUM('Fund NAV'!$C$6:E6) -> 0 | F6: =SUM('Fund NAV'!$C$6:F6) -> 0
B7: Cumulative net gains (gains less fees) | C7: =SUM('Fund NAV'!$C$7:C7)-SUM('Fund NAV'!$C$8:C8) -> 0 | D7: =SUM('Fund NAV'!$C$7:D7)-SUM('Fund NAV'!$C$8:D8) -> 0 | E7: =SUM('Fund NAV'!$C$7:E7)-SUM('Fund NAV'!$C$8:E8) -> 0 | F7: =SUM('Fund NAV'!$C$7:F7)-SUM('Fund NAV'!$C$8:F8) -> 0
B8: Cumulative distributable value (capital + net gains) | C8: =C6+C7 -> 0 | D8: =D6+D7 -> 0 | E8: =E6+E7 -> 0 | F8: =F6+F7 -> 0
B10: Cumulative waterfall (hurdle/carry/catch-up % from Fee Waterfall tab)
B11: Return of capital (cumulative) | C11: =MIN(C8,C6) -> 0 | D11: =MIN(D8,D6) -> 0 | E11: =MIN(E8,E6) -> 0 | F11: =MIN(F8,F6) -> 0
B12: Preferred return (cumulative) | C12: =MIN(MAX(C8-C11,0),C6*'Fee Waterfall'!$C$7) -> 0 | D12: =MIN(MAX(D8-D11,0),D6*'Fee Waterfall'!$C$7) -> 0 | E12: =MIN(MAX(E8-E11,0),E6*'Fee Waterfall'!$C$7) -> 0 | F12: =MIN(MAX(F8-F11,0),F6*'Fee Waterfall'!$C$7) -> 0
B13: GP catch-up tranche (cumulative) | C13: =IF('Fee Waterfall'!$C$9<='Fee Waterfall'!$C$8,0,MIN(MAX(C8-C11-C12,0),C12*'Fee Waterfall'!$C$8/('Fee Waterfall'!$C$9-'Fee Waterfall'!$C$8))) -> 0 | D13: =IF('Fee Waterfall'!$C$9<='Fee Waterfall'!$C$8,0,MIN(MAX(D8-D11-D12,0),D12*'Fee Waterfall'!$C$8/('Fee Waterfall'!$C$9-'Fee Waterfall'!$C$8))) -> 0 | E13: =IF('Fee Waterfall'!$C$9<='Fee Waterfall'!$C$8,0,MIN(MAX(E8-E11-E12,0),E12*'Fee Waterfall'!$C$8/('Fee Waterfall'!$C$9-'Fee Waterfall'!$C$8))) -> 0 | F13: =IF('Fee Waterfall'!$C$9<='Fee Waterfall'!$C$8,0,MIN(MAX(F8-F11-F12,0),F12*'Fee Waterfall'!$C$8/('Fee Waterfall'!$C$9-'Fee Waterfall'!$C$8))) -> 0
B14: GP share of catch-up | C14: =C13*'Fee Waterfall'!$C$9 -> 0 | D14: =D13*'Fee Waterfall'!$C$9 -> 0 | E14: =E13*'Fee Waterfall'!$C$9 -> 0 | F14: =F13*'Fee Waterfall'!$C$9 -> 0
B15: Remainder above catch-up (cumulative) | C15: =MAX(C8-C11-C12-C13,0) -> 0 | D15: =MAX(D8-D11-D12-D13,0) -> 0 | E15: =MAX(E8-E11-E12-E13,0) -> 0 | F15: =MAX(F8-F11-F12-F13,0) -> 0
B16: GP share of remainder | C16: =C15*'Fee Waterfall'!$C$8 -> 0 | D16: =D15*'Fee Waterfall'!$C$8 -> 0 | E16: =E15*'Fee Waterfall'!$C$8 -> 0 | F16: =F15*'Fee Waterfall'!$C$8 -> 0
B17: Cumulative GP carry earned through this period | C17: =C14+C16 -> 0 | D17: =D14+D16 -> 0 | E17: =E14+E16 -> 0 | F17: =F14+F16 -> 0
B19: Incremental GP carry this period | C19: =C17 -> 0 | D19: =D17-C17 -> 0 | E19: =E17-D17 -> 0 | F19: =F17-E17 -> 0
B20: Running total carry paid to GP | C20: =SUM($C$19:C19) -> 0 | D20: =SUM($C$19:D19) -> 0 | E20: =SUM($C$19:E19) -> 0 | F20: =SUM($C$19:F19) -> 0
B21: Clawback status | C21: =IF(C19<0,"CLAWBACK — GP owes $"&TEXT(-C19,"#,##0")&" back to LPs","-") -> - | D21: =IF(D19<0,"CLAWBACK — GP owes $"&TEXT(-D19,"#,##0")&" back to LPs","-") -> - | E21: =IF(E19<0,"CLAWBACK — GP owes $"&TEXT(-E19,"#,##0")&" back to LPs","-") -> - | F21: =IF(F19<0,"CLAWBACK — GP owes $"&TEXT(-F19,"#,##0")&" back to LPs","-") -> -

Sheet Performance Attribution
B2: Performance Attribution
B4: Position/Strategy | C4: Contribution ($) | D4: Contribution (%) | E4: Weight (%) | F4: Notes
B5: [fill in] | C5: 0 | D5: 0 | E5: 0
B6: [fill in] | C6: 0 | D6: 0 | E6: 0
B7: [fill in] | C7: 0 | D7: 0 | E7: 0
B8: [fill in] | C8: 0 | D8: 0 | E8: 0
B9: [fill in] | C9: 0 | D9: 0 | E9: 0
B10: [fill in] | C10: 0 | D10: 0 | E10: 0
B11: [fill in] | C11: 0 | D11: 0 | E11: 0
B12: Total fund return | C12: =SUM(C5:C11) -> 0

Sheet Fund Performance
B2: Fund Performance — LP Reporting Metrics
B4: Uses the period cash flows and ending NAV from the Fund NAV tab.
C6: Period 0 | D6: Period 1 | E6: Period 2 | F6: Period 3
B7: LP net cash flow (distributions - contributions) | C7: ='Fund NAV'!C9-'Fund NAV'!C6 -> 0 | D7: ='Fund NAV'!D9-'Fund NAV'!D6 -> 0 | E7: ='Fund NAV'!E9-'Fund NAV'!E6 -> 0 | F7: ='Fund NAV'!F9-'Fund NAV'!F6 -> 0
B8: + terminal NAV added to final period | C8: ='Fund NAV'!F10 -> 0
B9: LP cash flow incl. terminal value (for IRR) | C9: =C7 -> 0 | D9: =D7 -> 0 | E9: =E7 -> 0 | F9: =F7+C8 -> 0
B12: Outputs
B13: Cumulative capital called | C13: =SUM('Fund NAV'!C6:F6) -> 0
B14: Cumulative distributions | C14: =SUM('Fund NAV'!C9:F9) -> 0
B15: Current NAV (residual value) | C15: ='Fund NAV'!F10 -> 0
B16: DPI (Distributions to Paid-In) | C16: =IFERROR(C14/C13,"-") -> -
B17: RVPI (Residual Value to Paid-In) | C17: =IFERROR(C15/C13,"-") -> -
B18: TVPI (Total Value to Paid-In = DPI + RVPI) | C18: =IFERROR(C16+C17,"-") -> - | D18: Headline LP metric — total value (realized + unrealized) per dollar called
B19: Net IRR to LPs (periodic, undated) | C19: =IFERROR(IRR(C9:F9),"-") -> - | D19: Treats each period as evenly spaced — use XIRR with real dates for called capital at irregular intervals

Sheet Sources
B2: Sources
B3: What each material assumption or convention in this model comes from.
B5: Assumption / convention | C5: Source | D5: As of | E5: Note
B6: Waterfall structure (ROC -> pref -> GP catch-up -> carry split) | C6: Standard private-fund LPA waterfall mechanics | D6: Standard practice | E6: Whole-fund/European structure (cumulative), not deal-by-deal/American
B7: General catch-up formula for an arbitrary catch-up rate | C7: Derived from the target-carry identity GP_catchup/(pref+catchup)=carry%, solved for a catch-up tranche paid at rate g | D7: Derived, not copied from a single source | E7: Collapses to the standard 100%-catch-up formula when the catch-up rate = 100%
B8: Default fee terms (2% mgmt, 8% hurdle, 20% carry, 100% catch-up) | C8: Common industry-standard private-fund terms | D8: Standard practice | E8: Illustrative defaults; replace with the actual LPA's terms
B9: TVPI/DPI/RVPI and periodic IRR | C9: Standard LP-reporting metric definitions (ILPA-style) | D9: Standard practice | E9: Periodic IRR treats periods as evenly spaced -- use XIRR with real dates for irregular capital calls

Sheet Checks
B2: Checks
B3: Live reconciliation identities -- independent of the model's own formulas, must tie.
B5: Check | C5: Result | D5: Passes when
B6: Waterfall conserves: GP take + LP take = total distributable value (Fee Waterfall) | C6: ='Fee Waterfall'!C23+'Fee Waterfall'!C24-'Fee Waterfall'!C10 -> 0 | D6: 0 (exact) -- every dollar of distributable value lands with either the GP or the LPs
B7: Cumulative carry reconstructs from its own increments (Period 3) | C7: ='GP Carry & Clawback'!F20-'GP Carry & Clawback'!F17 -> 0 | D7: 0 (exact) -- the running total of incremental carry must equal the cumulative figure it was built from
B8: GP catch-up tranche is zero whenever catch-up % <= carry % (guards the division) | C8: =IF('Fee Waterfall'!C9<='Fee Waterfall'!C8,'Fee Waterfall'!C16=0,TRUE()) -> TRUE | D8: TRUE
B9: TVPI = DPI + RVPI identity | C9: =IFERROR('Fund Performance'!C18-('Fund Performance'!C16+'Fund Performance'!C17),"-") -> - | D9: 0 (exact) once capital has been called; "-" on a blank template

Sheet RefreshLog
B2: Refresh Log
B4: Date | C4: Trigger | D4: What changed | E4: Reviewer notes | F4: Next check
