Workbook

Sheet Cover
B2: [BOND/CURVE] — Fixed Income Model
B4: Instrument: | C4: [fill in]
B5: Issuer / sector: | C5: [fill in]
B6: Last refreshed: | C6: [date]
B7: Refresh cadence: | C7: Weekly

Sheet Bond Pricing
B2: Bond Pricing
B5: Face value ($) | C5: 1000
B6: Coupon rate (annual, %) | C6: 0.05
B7: Coupon frequency (payments/yr) | C7: 2
B8: Years to maturity | C8: 10
B9: Yield to maturity (annual, %) | C9: 0.055
B11: Price (using PV formula) | C11: =-PV(C9/C7,C7*C8,C5*C6/C7,C5) -> 961.93187 | D11: PV(YTM per period, n periods, coupon per period, face value)
B12: Price as % of par | C12: =IFERROR(C11/C5,"-") -> 0.96193187
B13: Current yield (annual coupon / price) | C13: =IFERROR(C5*C6/C11,"-") -> 0.051978733

Sheet Duration & Convexity
B2: Duration & Convexity
B4: Modified duration (approx., via price shock)
B5: Yield shock (bp) for numerical estimate | C5: 50
B6: Price at YTM - shock | C6: =-PV(('Bond Pricing'!C9-C5/10000)/'Bond Pricing'!C7,'Bond Pricing'!C7*'Bond Pricing'!C8,'Bond Pricing'!C5*'Bond Pricing'!C6/'Bond Pricing'!C7,'Bond Pricing'!C5) -> 1000
B7: Price at YTM + shock | C7: =-PV(('Bond Pricing'!C9+C5/10000)/'Bond Pricing'!C7,'Bond Pricing'!C7*'Bond Pricing'!C8,'Bond Pricing'!C5*'Bond Pricing'!C6/'Bond Pricing'!C7,'Bond Pricing'!C5) -> 925.61263
B8: Modified duration = (P- - P+) / (2 x P0 x shock in decimal) | C8: =IFERROR((C6-C7)/(2*'Bond Pricing'!C11*(C5/10000)),"-") -> 7.733123
B9: Convexity = (P- + P+ - 2xP0) / (P0 x shock^2) | C9: =IFERROR((C6+C7-2*'Bond Pricing'!C11)/('Bond Pricing'!C11*(C5/10000)^2),"-") -> 72.723918
B10: Est. price change for 100bp move (duration + convexity) | C10: =IFERROR(-C8*0.01+0.5*C9*0.01^2,"-") -> -0.073695034

Sheet Yield Curve
B2: Yield Curve & Spread Analysis
B4: Tenor | C4: Benchmark yield | D4: Instrument spread (bp) | E4: All-in yield
B5: 3M | C5: 0 | D5: 0 | E5: =C5+D5/10000 -> 0
B6: 2Y | C6: 0 | D6: 0 | E6: =C6+D6/10000 -> 0
B7: 5Y | C7: 0 | D7: 0 | E7: =C7+D7/10000 -> 0
B8: 10Y | C8: 0 | D8: 0 | E8: =C8+D8/10000 -> 0
B9: 30Y | C9: 0 | D9: 0 | E9: =C9+D9/10000 -> 0
B11: 2s10s spread (bp) | C11: =(C7-C6)*10000 -> 0 | D11: Negative = inverted curve

Sheet Total Return Scenarios
B2: 1-Year Total Return Under Rate Shocks
B4: Uses duration/convexity from the Duration & Convexity tab plus current yield as the income component — same approximation as that tab's single 100bp estimate, extended across a scenario grid.
B6: Parallel shift (bp) | C6: -100 | D6: -50 | E6: -25 | F6: 0 | G6: 25 | H6: 50 | I6: 100
B7: Price return (duration + convexity) | C7: =IFERROR(-'Duration & Convexity'!$C$8*(C6/10000)+0.5*'Duration & Convexity'!$C$9*(C6/10000)^2,"-") -> 0.080967426 | D7: =IFERROR(-'Duration & Convexity'!$C$8*(D6/10000)+0.5*'Duration & Convexity'!$C$9*(D6/10000)^2,"-") -> 0.039574664 | E7: =IFERROR(-'Duration & Convexity'!$C$8*(E6/10000)+0.5*'Duration & Convexity'!$C$9*(E6/10000)^2,"-") -> 0.01956007 | F7: =IFERROR(-'Duration & Convexity'!$C$8*(F6/10000)+0.5*'Duration & Convexity'!$C$9*(F6/10000)^2,"-") -> 0 | G7: =IFERROR(-'Duration & Convexity'!$C$8*(G6/10000)+0.5*'Duration & Convexity'!$C$9*(G6/10000)^2,"-") -> -0.019105545 | H7: =IFERROR(-'Duration & Convexity'!$C$8*(H6/10000)+0.5*'Duration & Convexity'!$C$9*(H6/10000)^2,"-") -> -0.037756566 | I7: =IFERROR(-'Duration & Convexity'!$C$8*(I6/10000)+0.5*'Duration & Convexity'!$C$9*(I6/10000)^2,"-") -> -0.073695034
B8: Income return (current yield) | C8: ='Bond Pricing'!$C$13 -> 0.051978733 | D8: ='Bond Pricing'!$C$13 -> 0.051978733 | E8: ='Bond Pricing'!$C$13 -> 0.051978733 | F8: ='Bond Pricing'!$C$13 -> 0.051978733 | G8: ='Bond Pricing'!$C$13 -> 0.051978733 | H8: ='Bond Pricing'!$C$13 -> 0.051978733 | I8: ='Bond Pricing'!$C$13 -> 0.051978733
B9: Total return | C9: =C7+C8 -> 0.13294616 | D9: =D7+D8 -> 0.091553397 | E9: =E7+E8 -> 0.071538803 | F9: =F7+F8 -> 0.051978733 | G9: =G7+G8 -> 0.032873188 | H9: =H7+H8 -> 0.014222167 | I9: =I7+I8 -> -0.021716301

Sheet Accrued Interest & Settlement
B2: Accrued Interest & Clean/Dirty Price
B4: Inputs
B5: Day-count convention (30/360 or Actual/Actual) | C5: 30/360
B6: Last coupon date | C6: 46023
B7: Next coupon date | C7: 46204
B8: Settlement date | C8: 46113
B10: Day Count
B11: Days accrued (last coupon -> settlement) | C11: =IF($C$5="30/360",DAYS360(C6,C8),C8-C6) -> 90
B12: Days in full coupon period (last coupon -> next coupon) | C12: =IF($C$5="30/360",DAYS360(C6,C7),C7-C6) -> 180
B13: Accrual fraction of the period | C13: =IFERROR(C11/C12,"-") -> 0.5
B15: Accrued Interest & Invoice Price
B16: Periodic coupon (from Bond Pricing) | C16: ='Bond Pricing'!C5*'Bond Pricing'!C6/'Bond Pricing'!C7 -> 25
B17: Accrued interest | C17: =IFERROR(C16*C13,"-") -> 12.5
B18: Clean price (from Bond Pricing — quoted market price) | C18: ='Bond Pricing'!C11 -> 961.93187
B19: Dirty / invoice price (clean + accrued — what the buyer actually pays) | C19: =IFERROR(C18+C17,"-") -> 974.43187 | D19: This is the number that actually settles — quoting only the clean price is a market convention, not the real cash flow

Sheet RefreshLog
B2: Refresh Log
B4: Date | C4: Trigger | D4: What changed | E4: Reviewer notes | F4: Next check
