Workbook

Sheet Cover
B2: [COMPANY] — Venture Capital Model
B4: Sector: | C4: [fill in]
B5: Current stage: | C5: Seed / A / B / C / Growth
B6: Last refreshed: | C6: [date]
B7: Next round expected: | C7: [date]
B8: Refresh cadence: | C8: Weekly

Sheet Cap Table
B2: Capitalization Table
B4: Holder / Class | C4: Shares | D4: % Fully Diluted | E4: Price paid/sh | F4: Invested $ | G4: Class
B5: Founders (common) | C5: 0 | D5: =IFERROR(C5/$C$11,"-") -> - | E5: 0 | F5: =C5*E5 -> 0 | G5: Common/Pref
B6: Employee option pool | C6: 0 | D6: =IFERROR(C6/$C$11,"-") -> - | E6: 0 | F6: =C6*E6 -> 0 | G6: Common/Pref
B7: SAFE holders (pre-conversion) | C7: 0 | D7: =IFERROR(C7/$C$11,"-") -> - | E7: 0 | F7: =C7*E7 -> 0 | G7: Common/Pref
B8: Seed preferred | C8: 0 | D8: =IFERROR(C8/$C$11,"-") -> - | E8: 0 | F8: =C8*E8 -> 0 | G8: Common/Pref
B9: Series A preferred | C9: 0 | D9: =IFERROR(C9/$C$11,"-") -> - | E9: 0 | F9: =C9*E9 -> 0 | G9: Common/Pref
B10: Series B preferred | C10: 0 | D10: =IFERROR(C10/$C$11,"-") -> - | E10: 0 | F10: =C10*E10 -> 0 | G10: Common/Pref
B11: Total | C11: =SUM(C5:C10) -> 0 | F11: =SUM(F5:F10) -> 0

Sheet Round Modeling
B2: New Round Modeling
B4: Inputs | E4: Outputs
B5: Pre-money valuation | C5: 0 | E5: Post-money valuation | F5: =C5+C6 -> 0
B6: New money raised | C6: 0 | E6: Price per share | F6: =IFERROR(C5/C8,"-") -> -
B7: New option pool top-up % | C7: 0 | E7: New shares issued (investor) | F7: =IFERROR(C6/F6,"-") -> -
B8: Existing fully diluted shares | C8: 0 | E8: New pool shares (top-up) | F8: =IFERROR(C7*(C8+F7),"-") -> -
E9: Total post-round shares | F9: =IFERROR(C8+F7+F8,"-") -> -
E10: New investor ownership % | F10: =IFERROR(F7/F9,"-") -> -
E11: Existing holder dilution % | F11: =IFERROR(1-C8/F9,"-") -> -

Sheet SAFE Conversion
B2: SAFE / Convertible Note Conversion
B4: SAFE Terms | E4: At Priced Round
B5: SAFE investment amount | C5: 0 | E5: Priced round price/share | F5: ='Round Modeling'!F6 -> -
B6: Valuation cap | C6: 0 | E6: Cap price/share (cap / pre-round FD shares) | F6: =IFERROR(C6/'Round Modeling'!C8,"-") -> -
B7: Discount % | C7: 0 | E7: Discount price/share | F7: =IFERROR(F5*(1-C7),"-") -> -
E8: SAFE conversion price (lower of cap/discount/round) | F8: =IFERROR(MIN(IF(ISNUMBER(F5),F5,9E+099),IF(ISNUMBER(F6),F6,9E+099),IF(ISNUMBER(F7),F7,9E+099)),"-") -> 9e+99
E9: SAFE shares issued | F9: =IFERROR(C5/F8,"-") -> 0

Sheet Exit Waterfall
B2: Exit Proceeds Waterfall (1x non-participating pref)
B4: Class | C4: Invested $ | D4: Liq. pref (1x) | E4: As-converted % | F4: Pref-stack scenario | G4: As-converted scenario | H4: Actual proceeds
B5: Series B preferred | C5: ='Cap Table'!F10 -> 0 | D5: =C5 -> 0 | E5: =IFERROR('Cap Table'!D10,"-") -> - | F5: =MIN($C$15,D5) -> 0 | G5: =IFERROR($C$15*E5,"-") -> - | H5: =IF($C$15>SUM($D$5:$D$7),G5,F5) -> 0
B6: Series A preferred | C6: ='Cap Table'!F9 -> 0 | D6: =C6 -> 0 | E6: =IFERROR('Cap Table'!D9,"-") -> - | F6: =MIN(MAX($C$15-F5,0),D6) -> 0 | G6: =IFERROR($C$15*E6,"-") -> - | H6: =IF($C$15>SUM($D$5:$D$7),G6,F6) -> 0
B7: Seed preferred | C7: ='Cap Table'!F8 -> 0 | D7: =C7 -> 0 | E7: =IFERROR('Cap Table'!D8,"-") -> - | F7: =MIN(MAX($C$15-F5-F6,0),D7) -> 0 | G7: =IFERROR($C$15*E7,"-") -> - | H7: =IF($C$15>SUM($D$5:$D$7),G7,F7) -> 0
B8: Common (founders + pool) | C8: ='Cap Table'!F5+'Cap Table'!F6 -> 0 | D8: =C8 -> 0 | E8: =IFERROR('Cap Table'!D5+'Cap Table'!D6,"-") -> - | F8: =MAX(0,$C$15-F5-F6-F7) -> 0 | G8: =IFERROR($C$15*E8,"-") -> - | H8: =IF($C$15>SUM($D$5:$D$7),G8,F8) -> 0
B10: Regime: as-converted pays more fund-wide than the full pref stack? | C10: =IF($C$15>SUM(D5:D7),"YES — use as-converted","NO — use pref-stack") -> NO — use pref-stack
B11: Total distributed (check — should equal total exit proceeds) | C11: =SUM(H5:H8) -> 0
B13: Simplification: switches the WHOLE cap table between the pref-stack and as-converted scenario based on one global test (total proceeds vs. sum of all preferences), rather than letting each class elect independently. Real waterfalls often have junior classes convert while senior ones keep their pref, in the middle range between these two extremes — that requires testing conversion elections class by class (a small solver, not a single formula). This always ties to total proceeds and is exactly right at both extremes; treat the boundary/middle range as a case for a proper waterfall tool or counsel, not this template.
B15: Total exit proceeds | C15: 0

Sheet Comparable Financings
B2: Comparable Financings
B4: Company | C4: Round | D4: Date | E4: Pre-money | F4: Amount raised | G4: Lead investor
B5: [fill in] | C5: [fill in] | D5: [fill in] | E5: 0 | F5: 0 | G5: [fill in]
B6: [fill in] | C6: [fill in] | D6: [fill in] | E6: 0 | F6: 0 | G6: [fill in]
B7: [fill in] | C7: [fill in] | D7: [fill in] | E7: 0 | F7: 0 | G7: [fill in]
B8: [fill in] | C8: [fill in] | D8: [fill in] | E8: 0 | F8: 0 | G8: [fill in]
B9: [fill in] | C9: [fill in] | D9: [fill in] | E9: 0 | F9: 0 | G9: [fill in]
B10: [fill in] | C10: [fill in] | D10: [fill in] | E10: 0 | F10: 0 | G10: [fill in]
B11: [fill in] | C11: [fill in] | D11: [fill in] | E11: 0 | F11: 0 | G11: [fill in]
B12: [fill in] | C12: [fill in] | D12: [fill in] | E12: 0 | F12: 0 | G12: [fill in]

Sheet RefreshLog
B2: Refresh Log
B4: Date | C4: Trigger | D4: What changed | E4: Reviewer notes | F4: Next check
