Workbook

Sheet Cover
B2: [COMPANY] — Fintech / Payments Model
B4: Business model: | C4: Payments / lending / neobank / infra
B5: Regulatory status: | C5: [licensed / partner bank / sponsor bank]
B6: Last refreshed: | C6: [date]
B7: Next cohort/unit-economics review: | C7: [date]
B8: Refresh cadence: | C8: Weekly

Sheet Unit Economics
B2: Unit Economics
B5: Total payment volume, TPV ($/mo) | C5: 0
B6: Take rate (%) | C6: 0.025
B7: Interchange/processing cost (% of TPV) | C7: 0.015
B8: CAC ($ per customer) | C8: 0
B9: Avg monthly revenue per customer ($) | C9: 0
B10: Monthly gross margin per customer (%) | C10: 0.6
B11: Monthly churn rate (%) | C11: 0.03
B13: Outputs
B14: Revenue (take rate x TPV) | C14: =C5*C6 -> 0
B15: Processing cost ($) | C15: =C5*C7 -> 0
B16: Net revenue after processing cost | C16: =C14-C15 -> 0
B17: Customer lifetime (months) = 1/churn | C17: =IFERROR(1/C11,"-") -> 33.333333
B18: LTV = monthly rev x gross margin x lifetime | C18: =C9*C10*C17 -> 0
B19: LTV / CAC ratio | C19: =IFERROR(C18/C8,"-") -> - | D19: Rule of thumb: >3x is healthy, <1x means losing money per customer
B20: CAC payback period (months) | C20: =IFERROR(C8/(C9*C10),"-") -> -

Sheet Interchange Economics
B2: Interchange Economics — Durbin-Regulated vs. Exempt
B3: Reg II caps DEBIT interchange for issuers with >$10B in assets. Issuers below that threshold are EXEMPT and can charge network-published unregulated rates -- roughly 3x higher on typical transaction sizes. This is the actual structural reason many neobanks partner with a small "sponsor bank" rather than becoming a bank themselves: it isn't just charter overhead, it's interchange economics.
B5: Inputs
B6: Average transaction size ($) | C6: 40
B7: TPV this period ($/mo) | C7: ='Unit Economics'!C5 -> 0
B8: Estimated transaction count | C8: =IFERROR(C7/C6,"-") -> 0
B10: Regulated (Durbin-capped, issuing bank > $10B assets)
B11: Interchange per transaction (Reg II cap: $0.22 + 0.05% x txn size) | C11: =0.22+0.0005*C6 -> 0.24
B12: Effective interchange rate (% of TPV) | C12: =IFERROR(C11/C6,"-") -> 0.006
B13: Interchange income/cost this period (rate x TPV) | C13: =IFERROR(C12*C7,"-") -> 0
B15: Exempt (Durbin-exempt, issuing bank < $10B assets -- typical sponsor-bank structure)
B16: Interchange per transaction (network unregulated rate: $0.04 + 1.65% x txn size) | C16: =0.04+0.0165*C6 -> 0.7
B17: Effective interchange rate (% of TPV) | C17: =IFERROR(C16/C6,"-") -> 0.0175
B18: Interchange income/cost this period (rate x TPV) | C18: =IFERROR(C17*C7,"-") -> 0
B20: Exempt vs. Regulated Advantage
B21: $ difference this period (exempt - regulated) | C21: =C18-C13 -> 0
B22: Annualized $ difference | C22: =C21*12 -> 0
B23: Exempt uplift (%) | C23: =IFERROR(C18/C13-1,"-") -> - | D23: This is a per-transaction-size-dependent advantage -- it shrinks toward zero as average ticket size grows, since the ad-valorem component matters more than the fixed component at high ticket sizes.

Sheet Cohort Retention
B2: Cohort Retention (% of cohort still active)
B4: Cohort | C4: M0 | D4: M1 | E4: M2 | F4: M3 | G4: M4 | H4: M5 | I4: M6 | J4: M7
B5: Jan cohort | C5: 1 | D5: 0 | E5: 0 | F5: 0 | G5: 0 | H5: 0 | I5: 0 | J5: 0
B6: Feb cohort | C6: 1 | D6: 0 | E6: 0 | F6: 0 | G6: 0 | H6: 0 | I6: 0 | J6: 0
B7: Mar cohort | C7: 1 | D7: 0 | E7: 0 | F7: 0 | G7: 0 | H7: 0 | I7: 0 | J7: 0
B8: Apr cohort | C8: 1 | D8: 0 | E8: 0 | F8: 0 | G8: 0 | H8: 0 | I8: 0 | J8: 0
B9: Average retention | C9: =AVERAGE(C5:C8) -> 1 | D9: =AVERAGE(D5:D8) -> 0 | E9: =AVERAGE(E5:E8) -> 0 | F9: =AVERAGE(F5:F8) -> 0 | G9: =AVERAGE(G5:G8) -> 0 | H9: =AVERAGE(H5:H8) -> 0 | I9: =AVERAGE(I5:I8) -> 0 | J9: =AVERAGE(J5:J8) -> 0
B10: Curve-implied LTV multiplier (sum of avg retention, M0-M7) | C10: =SUM(C9:J9) -> 1
B11: M0 always = 100% by definition. Fill subsequent months as cohorts age.
B12: Retention-curve LTV = monthly rev x gross margin x this multiplier — compare to the steady-state 1/churn LTV on Unit Economics; a big gap means churn isn't actually constant month to month (usually front-loaded), and the curve number is the more honest one.

Sheet Fraud & Risk
B2: Fraud, Chargeback & Credit Loss
B4: Inputs
B5: Total payment volume, TPV ($/mo) | C5: 0
B6: Fraud loss rate (bps of TPV) | C6: 8
B7: Chargeback count (this period) | C7: 0
B8: Chargeback cost per incident ($, fee + lost goods) | C8: 25
B9: Credit losses — lending book only, if applicable ($) | C9: 0
B11: Outputs
B12: Fraud loss ($) | C12: =C5*C6/10000 -> 0 | D12: bps convention: 8 bps = 0.08%
B13: Chargeback cost ($) | C13: =C7*C8 -> 0
B14: Total risk-related loss ($) | C14: =C12+C13+C9 -> 0
B15: Total loss as % of net revenue | C15: =IFERROR(C14/'Unit Economics'!C16,"-") -> - | D15: Card networks typically flag issuers/acquirers above ~90-100bps fraud-to-TPV as a monitoring risk

Sheet Sources
B2: Sources
B3: What each material assumption or convention in this model comes from.
B5: Assumption / convention | C5: Source | D5: As of | E5: Note
B6: Reg II regulated debit interchange cap ($0.22 + 0.05%) | C6: Federal Reserve Regulation II (Durbin Amendment implementing rule), covered issuers >$10B in assets | D6: Statutory/regulatory cap | E6: Includes the optional $0.01 fraud-prevention adjustment folded into the $0.22 base; actual issuer cap can vary slightly by fraud-prevention-standard compliance
B7: Durbin-exempt unregulated debit rate ($0.04 + 1.65%) | C7: Network-published unregulated debit interchange schedules (Visa/Mastercard), issuers <$10B in assets | D7: Standard practice / network schedules | E7: Illustrative approximation of published schedules -- actual rates vary by card program, merchant category, and network
B8: LTV = monthly revenue x gross margin x customer lifetime (1/churn) | C8: Standard SaaS/subscription LTV formula adapted for fintech unit economics | D8: Standard practice | E8: Assumes constant monthly churn -- the Cohort Retention tab's curve-implied multiplier is the more honest number when churn is front-loaded
B9: Fraud loss rate in bps of TPV | C9: Standard payments-industry convention | D9: Standard practice | E9: Card networks typically flag issuers/acquirers above ~90-100bps fraud-to-TPV as a monitoring risk, per the Fraud & Risk tab's note

Sheet Checks
B2: Checks
B3: Live reconciliation identities -- independent of the model's own formulas, must tie.
B5: Check | C5: Result | D5: Passes when
B6: Exempt interchange income exceeds regulated at typical ticket sizes ($40 test) | C6: =IF('Interchange Economics'!C6=40,'Interchange Economics'!C18>'Interchange Economics'!C13,TRUE()) -> FALSE | D6: TRUE at the $40 default -- confirms the Durbin-exempt advantage is actually wired, not just labeled
B7: Interchange income ties: rate x TPV = per-txn fee x transaction count (Regulated) | C7: =IFERROR('Interchange Economics'!C13-('Interchange Economics'!C11*'Interchange Economics'!C8),"-") -> 0 | D7: 0 (exact) once TPV is populated
B8: Interchange income ties: rate x TPV = per-txn fee x transaction count (Exempt) | C8: =IFERROR('Interchange Economics'!C18-('Interchange Economics'!C16*'Interchange Economics'!C8),"-") -> 0 | D8: 0 (exact) once TPV is populated
B9: Cohort M0 retention is always 100% by definition | C9: =IF(COUNTIF('Cohort Retention'!C5:C8,1)=4,TRUE(),FALSE()) -> TRUE | D9: TRUE

Sheet RefreshLog
B2: Refresh Log
B4: Date | C4: Trigger | D4: What changed | E4: Reviewer notes | F4: Next check
